Workbook

Sheet Items
A1: Nom | B1: Type | C1: Rareté | D1: Prix de base | E1: Effet | F1: Valeur effet
A2: Plasma Pistol MK-I | B2: weapon | C2: common | D2: 100 | E2: attack_boost | F2: 5
A3: Vibro-Blade | B3: weapon | C3: common | D3: 200 | E3: attack_boost | F3: 8
A4: Budget Arms Unity+ | B4: weapon | C4: common | D4: 350 | E4: attack_boost | F4: 11
A5: Neural Disruptor | B5: weapon | C5: uncommon | D5: 500 | E5: attack_boost | F5: 15
A6: Kang Tao Shock Carbine | B6: weapon | C6: uncommon | D6: 1400 | E6: attack_boost | F6: 22
A7: Railgun X-7 | B7: weapon | C7: rare | D7: 1500 | E7: attack_boost | F7: 25
A8: Militech Crusher Custom | B8: weapon | C8: rare | D8: 8500 | E8: attack_boost | F8: 38
A9: Void Cannon | B9: weapon | C9: epic | D9: 5000 | E9: attack_boost | F9: 50
A10: Arasaka Revenant Smartgun | B10: weapon | C10: epic | D10: 52000 | E10: attack_boost | F10: 78
A11: OMEGA Protocol | B11: weapon | C11: legendary | D11: 20000 | E11: attack_boost | F11: 100
A12: Blackwall Breacher | B12: weapon | C12: legendary | D12: 240000 | E12: attack_boost | F12: 155
A13: Kevlar Vest | B13: armor | C13: common | D13: 80 | E13: defense_boost | F13: 3
... A33: Relic Overclock Kernel | B33: implant | C33: legendary | D33: 260000 | E33: click_multiplier | F33: 82
A34: Static Mohawk | B34: clothes_hair | C34: common | D34: 900
A35: Acid Bob | B35: clothes_hair | C35: uncommon | D35: 2600
A36: Ghost Braids | B36: clothes_hair | C36: rare | D36: 8800
A37: Chromehawk Crown | B37: clothes_hair | C37: epic | D37: 24000
A38: Kiroshi Night Visor | B38: clothes_face | C38: common | D38: 1200
A39: Carbon Half Mask | B39: clothes_face | C39: uncommon | D39: 3100
A40: Oni Signal Mask | B40: clothes_face | C40: rare | D40: 9600
A41: Blackwall Respirator | B41: clothes_face | C41: epic | D41: 27000
A42: Hexline Jacket | B42: clothes_outer | C42: common | D42: 1800
A43: Nightglass Trench | B43: clothes_outer | C43: rare | D43: 11000
A44: Chrome Bolero | B44: clothes_outer | C44: epic | D44: 28500
A45: Holo Weave Shell | B45: clothes_outer | C45: legendary | D45: 72000
... A49: Exo-Leg Rails | B49: clothes_legs | C49: epic | D49: 32000
A50: Stim Pack | B50: consumable | C50: common | D50: 25 | E50: hp_restore | F50: 30
A51: MedGel Capsule | B51: consumable | C51: uncommon | D51: 80 | E51: hp_restore | F51: 75
A52: Phoenix Serum | B52: consumable | C52: rare | D52: 300 | E52: hp_restore | F52: 999
A53: CyberBoost Energy | B53: consumable | C53: uncommon | D53: 100 | E53: temp_click_boost | F53: 2
A54: XP Chip | B54: consumable | C54: rare | D54: 400 | E54: xp_boost | F54: 500
A55: Neural Respec Chip | B55: consumable | C55: legendary | D55: 50000 | E55: talent_respec | F55: 1
A56: Finger Servos | B56: upgrade | C56: common | D56: 5000 | E56: permanent_click | F56: 1
A57: Haptic Amplifier | B57: upgrade | C57: uncommon | D57: 50000 | E57: permanent_click | F57: 3
A58: Neural Click Matrix | B58: upgrade | C58: rare | D58: 500000 | E58: permanent_click | F58: 5
A59: Quantum Tap Interface | B59: upgrade | C59: epic | D59: 5000000 | E59: permanent_click | F59: 8

Sheet Shop
A1: Item | B1: Prix base | C1: Prix shop (override) | D1: Stock | E1: Actif
A2: Plasma Pistol MK-I | B2: 100 | E2: TRUE
A3: Vibro-Blade | B3: 200 | E3: TRUE
A4: Budget Arms Unity+ | B4: 350 | E4: TRUE
A5: Neural Disruptor | B5: 500 | D5: 5 | E5: TRUE
A6: Kang Tao Shock Carbine | B6: 1400 | D6: 5 | E6: TRUE
A7: Railgun X-7 | B7: 1500 | D7: 3 | E7: TRUE
A8: Militech Crusher Custom | B8: 8500 | D8: 3 | E8: TRUE
A9: Void Cannon | B9: 5000 | D9: 1 | E9: TRUE
A10: Arasaka Revenant Smartgun | B10: 52000 | C10: 64000 | D10: 1 | E10: TRUE
A11: Blackwall Breacher | B11: 240000 | C11: 290000 | D11: 1 | E11: TRUE
A12: Kevlar Vest | B12: 80 | E12: TRUE
A13: Tyger Claws Reinforced Coat | B13: 300 | E13: TRUE
A14: Nanoweave Jacket | B14: 400 | D14: 5 | E14: TRUE
A15: Trauma Team Ballistic Mesh | B15: 1250 | D15: 5 | E15: TRUE
A16: Titanium Exosuit | B16: 1200 | D16: 3 | E16: TRUE
A17: Militech Bastion Frame | B17: 7800 | D17: 3 | E17: TRUE
A18: Arasaka Specter Weave | B18: 47000 | C18: 58000 | D18: 1 | E18: TRUE
A19: Mikoshi Nullskin | B19: 210000 | C19: 260000 | D19: 1 | E19: TRUE
A20: Reflex Booster v1 | B20: 150 | E20: TRUE
A21: Kiroshi Pulse Sync | B21: 400 | E21: TRUE
A22: Neural Accelerator | B22: 600 | D22: 5 | E22: TRUE
A23: Sandevistan Lite | B23: 1600 | D23: 5 | E23: TRUE
A24: Synaptic Overdrive | B24: 2000 | D24: 2 | E24: TRUE
A25: QianT Synapse Rail | B25: 9200 | D25: 3 | E25: TRUE
A26: Mantis Driver Suite | B26: 56000 | C26: 62000 | D26: 1 | E26: TRUE
A27: Militech Apogee Sandevistan | B27: 320000 | C27: 380000 | D27: 1 | E27: TRUE
A28: Relic Overclock Kernel | B28: 260000 | C28: 330000 | D28: 1 | E28: TRUE
A29: Stim Pack | B29: 25 | E29: TRUE
A30: MedGel Capsule | B30: 80 | E30: TRUE
A31: Phoenix Serum | B31: 300 | D31: 10 | E31: TRUE
A32: CyberBoost Energy | B32: 100 | E32: TRUE
A33: Finger Servos | B33: 5000 | C33: 5000 | D33: 10 | E33: TRUE
A34: Haptic Amplifier | B34: 50000 | C34: 50000 | D34: 10 | E34: TRUE
A35: Neural Click Matrix | B35: 500000 | C35: 500000 | D35: 10 | E35: FALSE
A36: Quantum Tap Interface | B36: 5000000 | C36: 5000000 | D36: 10 | E36: FALSE
A37: Neural Respec Chip | B37: 50000 | C37: 50000 | E37: TRUE
A38: Static Mohawk | B38: 900 | E38: TRUE
A39: Acid Bob | B39: 2600 | D39: 6 | E39: TRUE
A40: Ghost Braids | B40: 8800 | D40: 4 | E40: TRUE
A41: Chromehawk Crown | B41: 24000 | C41: 28000 | D41: 2 | E41: TRUE
A42: Kiroshi Night Visor | B42: 1200 | E42: TRUE
A43: Carbon Half Mask | B43: 3100 | D43: 6 | E43: TRUE
A44: Oni Signal Mask | B44: 9600 | D44: 4 | E44: TRUE
A45: Blackwall Respirator | B45: 27000 | C45: 32000 | D45: 2 | E45: TRUE
A46: Hexline Jacket | B46: 1800 | E46: TRUE
A47: Nightglass Trench | B47: 11000 | D47: 4 | E47: TRUE
A48: Chrome Bolero | B48: 28500 | C48: 33000 | D48: 2 | E48: TRUE
A49: Holo Weave Shell | B49: 72000 | C49: 79000 | D49: 1 | E49: TRUE
A50: Backalley Cargos | B50: 1400 | E50: TRUE
A51: Techwear Striders | B51: 4200 | D51: 6 | E51: TRUE
A52: Zero-G Runners | B52: 12500 | D52: 4 | E52: TRUE
A53: Exo-Leg Rails | B53: 32000 | C53: 36000 | D53: 2 | E53: TRUE

Sheet Ennemis
A1: Nom | B1: Tier | C1: HP | D1: ATK | E1: DEF | F1: XP | G1: Credits Min | H1: Credits Max | I1: Crit% | J1: CritDmg%
A2: Glitched Drone | B2: 1 | C2: 30 | D2: 5 | E2: 2 | F2: 10 | G2: 5 | H2: 15 | I2: 3 | J2: 130
A3: Neon Rat | B3: 1 | C3: 20 | D3: 8 | E3: 1 | F3: 8 | G3: 3 | H3: 10 | I3: 5 | J3: 140
A4: Street Thug | B4: 1 | C4: 50 | D4: 7 | E4: 3 | F4: 15 | G4: 10 | H4: 25 | I4: 4 | J4: 135
A5: Rogue AI Drone | B5: 2 | C5: 80 | D5: 15 | E5: 8 | F5: 30 | G5: 20 | H5: 50 | I5: 8 | J5: 155
A6: Cyber Jackal | B6: 2 | C6: 60 | D6: 20 | E6: 5 | F6: 25 | G6: 15 | H6: 40 | I6: 10 | J6: 160
A7: DataWraith | B7: 2 | C7: 70 | D7: 18 | E7: 10 | F7: 35 | G7: 25 | H7: 60 | I7: 7 | J7: 150
A8: Corp Security Bot | B8: 3 | C8: 150 | D8: 25 | E8: 20 | F8: 60 | G8: 50 | H8: 120 | I8: 10 | J8: 170
A9: Netrunner Assassin | B9: 3 | C9: 100 | D9: 35 | E9: 12 | F9: 70 | G9: 60 | H9: 150 | I9: 15 | J9: 180
A10: Mech Walker | B10: 3 | C10: 200 | D10: 30 | E10: 25 | F10: 80 | G10: 80 | H10: 200 | I10: 8 | J10: 200
A11: ARCHON | B11: 4 | C11: 500 | D11: 50 | E11: 30 | F11: 200 | G11: 300 | H11: 800 | I11: 12 | J11: 200
A12: Chrome Dragon | B12: 4 | C12: 800 | D12: 60 | E12: 40 | F12: 350 | G12: 500 | H12: 1500 | I12: 15 | J12: 220
A13: The Void King | B13: 4 | C13: 1200 | D13: 80 | E13: 50 | F13: 500 | G13: 1000 | H13: 3000 | I13: 20 | J13: 250
... A23: Soulkiller Prime | B23: 7 | C23: 9800 | D23: 285 | E23: 220 | F23: 2800 | G23: 32000 | H23: 55000 | I23: 28 | J23: 260

Sheet Loot Table
A1: Ennemi | B1: Item | C1: Chance de drop
A2: Glitched Drone | B2: Stim Pack | C2: 0.3
A3: Glitched Drone | B3: Finger Servos | C3: 0.1
A4: Neon Rat | B4: Stim Pack | C4: 0.2
A5: Street Thug | B5: Plasma Pistol MK-I | C5: 0.15
A6: Street Thug | B6: Kevlar Vest | C6: 0.1
A7: Rogue AI Drone | B7: Neural Disruptor | C7: 0.15
A8: Rogue AI Drone | B8: Neural Accelerator | C8: 0.1
A9: Cyber Jackal | B9: Nanoweave Jacket | C9: 0.15
A10: DataWraith | B10: Haptic Amplifier | C10: 0.12
A11: DataWraith | B11: MedGel Capsule | C11: 0.2
A12: Corp Security Bot | B12: Titanium Exosuit | C12: 0.12
A13: Netrunner Assassin | B13: Railgun X-7 | C13: 0.1
... A45: Soulkiller Prime | B45: Relic Overclock Kernel | C45: 0.08

Sheet Donjon
A1: Etage | B1: Nom | C1: Niveau min | D1: Ennemis | E1: Boss | F1: Joueurs min | G1: Joueurs max
A2: 1 | B2: Neon Alley | C2: 1 | D2: Glitched Drone, Neon Rat, Street Thug | F2: 1 | G2: 4
A3: 2 | B3: Abandoned Metro | C3: 3 | D3: Glitched Drone, Neon Rat, Street Thug, Rogue AI Drone | F3: 1 | G3: 4
A4: 3 | B4: Data Catacombs | C4: 5 | D4: Rogue AI Drone, Cyber Jackal, DataWraith | E4: ARCHON | F4: 1 | G4: 4
A5: 4 | B5: Corporate Spire - Lower | C5: 8 | D5: Cyber Jackal, DataWraith, Corp Security Bot, Netrunner Assassin | F5: 2 | G5: 4
A6: 5 | B6: Corporate Spire - Upper | C6: 10 | D6: Corp Security Bot, Netrunner Assassin, Mech Walker | E6: Chrome Dragon | F6: 2 | G6: 4
A7: 6 | B7: The Void | C7: 15 | D7: Mech Walker, ARCHON, Chrome Dragon | E7: The Void King | F7: 3 | G7: 4
A8: 7 | B8: Pacifica Black Site | C8: 20 | D8: Black ICE Hound, Maelstrom Ripper, Militech Suppressor | F8: 2 | G8: 4
A9: 8 | B9: Dogtown Kill Corridors | C9: 24 | D9: Black ICE Hound, Militech Suppressor, Arasaka Counter-Intel | E9: Cyberpsycho Dragoon | F9: 2 | G9: 4
A10: 9 | B10: Arasaka Counterintel Vault | C10: 29 | D10: Militech Suppressor, Arasaka Counter-Intel, Sandevistan Duelist, Cyberpsycho Dragoon | F10: 2 | G10: 4
A11: 10 | B11: Cynosure Relay | C11: 34 | D11: Arasaka Counter-Intel, Sandevistan Duelist, Cyberpsycho Dragoon, Cerberus Siege Frame | E11: Blackwall Seraph | F11: 3 | G11: 4
A12: 11 | B12: Mikoshi Access Spine | C12: 40 | D12: Cerberus Siege Frame, Blackwall Seraph, Mikoshi Warden | F12: 3 | G12: 4
A13: 12 | B13: Blackwall Breach | C13: 48 | D13: Blackwall Seraph, Mikoshi Warden, Soulkiller Prime | E13: Soulkiller Prime | F13: 4 | G13: 4

Sheet Companions
A1: Nom | B1: Rareté | C1: Type bonus | D1: Valeur bonus | E1: Prix
A2: Micro-Drone MK1 | B2: common | C2: cpc_flat | D2: 2 | E2: 500
A3: Rat Cybernétique | B3: common | C3: cps_flat | D3: 1 | E3: 800
A4: Bot Bouclier | B4: common | C4: def_flat | D4: 3 | E4: 600
A5: Falcon Electrique | B5: uncommon | C5: crit_chance | D5: 3 | E5: 2500
A6: Spider-Bot | B6: uncommon | C6: atk_flat | D6: 5 | E6: 3000
A7: Nanites Collecteurs | B7: uncommon | C7: cps_flat | D7: 3 | E7: 3500
A8: Drone Tactique V2 | B8: rare | C8: cpc_flat | D8: 8 | E8: 10000
A9: Loup Chrome | B9: rare | C9: atk_flat | D9: 10 | E9: 12000
A10: Medic-Bot | B10: rare | C10: hp_flat | D10: 50 | E10: 8000
A11: Phoenix Digital | B11: epic | C11: crit_chance | D11: 8 | E11: 35000
A12: Golem de Données | B12: epic | C12: def_flat | D12: 20 | E12: 40000
A13: NEXUS - IA Rogue | B13: legendary | C13: cpc_flat | D13: 20 | E13: 100000
A14: Dragon Holographique | B14: legendary | C14: crit_chance | D14: 15 | E14: 150000

Sheet Progression Niveaux
A1: Niveau | B1: XP pour next | C1: XP cumulé | D1: HP Max | E1: ATK | F1: DEF | G1: CPC | H1: CPS | I1: Crit% | J1: CritDmg% | K1: Talent Pts cumulés
A2: 1 | B2: 100 | C2: 0 | D2: 100 | E2: 10 | F2: 5 | G2: 1 | H2: 0 | I2: 0 | J2: 150 | K2: 1
A3: 2 | B3: 200 | C3: 100 | D3: 111 | E3: 12 | F3: 6 | G3: 1 | H3: 0 | I3: 0 | J3: 150 | K3: 2
A4: 3 | B4: 300 | C4: 300 | D4: 123 | E4: 14 | F4: 7 | G4: 2 | H4: 0 | I4: 0 | J4: 150 | K4: 3
A5: 4 | B5: 400 | C5: 600 | D5: 137 | E5: 16 | F5: 8 | G5: 2 | H5: 0 | I5: 0 | J5: 150 | K5: 4
A6: 5 | B6: 500 | C6: 1000 | D6: 152 | E6: 19 | F6: 10 | G6: 2 | H6: 0 | I6: 1 | J6: 155 | K6: 5
A7: 6 | B7: 600 | C7: 1500 | D7: 169 | E7: 22 | F7: 12 | G7: 3 | H7: 0 | I7: 1 | J7: 155 | K7: 6
A8: 7 | B8: 700 | C8: 2100 | D8: 187 | E8: 25 | F8: 14 | G8: 3 | H8: 0 | I8: 1 | J8: 155 | K8: 7
A9: 8 | B9: 800 | C9: 2800 | D9: 207 | E9: 28 | F9: 16 | G9: 3 | H9: 0 | I9: 1 | J9: 155 | K9: 8
A10: 9 | B10: 900 | C10: 3600 | D10: 228 | E10: 31 | F10: 18 | G10: 4 | H10: 0 | I10: 1 | J10: 155 | K10: 9
A11: 10 | B11: 1000 | C11: 4500 | D11: 251 | E11: 35 | F11: 21 | G11: 4 | H11: 1 | I11: 2 | J11: 160 | K11: 10
A12: 11 | B12: 1100 | C12: 5500 | D12: 275 | E12: 39 | F12: 24 | G12: 4 | H12: 1 | I12: 2 | J12: 160 | K12: 11
A13: 12 | B13: 1200 | C13: 6600 | D13: 301 | E13: 43 | F13: 27 | G13: 5 | H13: 1 | I13: 2 | J13: 160 | K13: 12
... A151: 150 | B151: 15000 | C151: 1117500 | D151: 18241 | E151: 2513 | F151: 2359 | G151: 51 | H151: 15 | I151: 30 | J151: 300 | K151: 150

Sheet Missions
A1: Nom | B1: Type | C1: Objectif | D1: Récompense type | E1: Récompense valeur
A2: Routine de hack | B2: click | C2: 100 | D2: credits | E2: 200
A3: Hack intensif | B3: click | C3: 500 | D3: credits | E3: 1000
A4: Overdrive | B4: click | C4: 1000 | D4: xp | E4: 500
A5: Nettoyage de rue | B5: kill | C5: 3 | D5: credits | E5: 500
A6: Chasseur de primes | B6: kill | C6: 10 | D6: credits | E6: 2000
A7: Exterminateur | B7: kill | C7: 20 | D7: xp | E7: 1000
A8: Exploration | B8: dungeon_clear | C8: 1 | D8: credits | E8: 800
A9: Plongee profonde | B9: dungeon_clear | C9: 3 | D9: credits | E9: 3000
A10: Premier million | B10: earn_credits | C10: 5000 | D10: xp | E10: 300
A11: Flux de données | B11: earn_credits | C11: 20000 | D11: credits | E11: 5000
A12: Gladiateur | B12: pvp_win | C12: 1 | D12: credits | E12: 1000
A13: Champion de l'arene | B13: pvp_win | C13: 3 | D13: credits | E13: 5000

Sheet Talents
A1: Tier | B1: Niveau requis | C1: Coût (PT) | D1: PT cumulés
A2: 1 | B2: 1 | C2: 1 | D2: 1
A3: 2 | B3: 5 | C3: 1 | D3: 2
A4: 3 | B4: 12 | C4: 1 | D4: 3
A5: 4 | B5: 20 | C5: 1 | D5: 4
A6: 5 | B6: 30 | C6: 1 | D6: 5
A7: 6 | B7: 38 | C7: 2 | D7: 7
A8: 7 | B8: 46 | C8: 2 | D8: 9
A9: 8 | B9: 54 | C9: 2 | D9: 11
A10: 9 | B10: 62 | C10: 2 | D10: 13
A11: 10 | B11: 70 | C11: 2 | D11: 15
A12: 11 | B12: 76 | C12: 3 | D12: 18
A13: 12 | B13: 82 | C13: 3 | D13: 21
... A21: 20 | B21: 150 | C21: 5 | D21: 55

Sheet Combat Skills
A1: Spec | B1: Skill | C1: Tier requis | D1: Type effet | E1: Valeur | F1: Durée (tours) | G1: Cooldown (tours)
A2: Hacker | B2: Breach Protocol | C2: 3 | D2: debuff_def | E2: 50 | F2: 2 | G2: 4
A3: Hacker | B3: Short Circuit | C3: 7 | D3: pure_damage | E3: 150 | F3: 0 | G3: 3
A4: Hacker | B4: Backdoor | C4: 12 | D4: steal_damage | E4: 120 | F4: 0 | G4: 4
A5: Hacker | B5: Kernel Panic | C5: 18 | D5: damage_stun | E5: 200 | F5: 1 | G5: 5
A6: Netrunner | B6: Ping Scan | C6: 3 | D6: guaranteed_crit | E6: 0 | F6: 1 | G6: 3
A7: Netrunner | B7: ICE Breaker | C7: 7 | D7: purge_damage | E7: 80 | F7: 0 | G7: 3
A8: Netrunner | B8: Neural Overload | C8: 12 | D8: damage_stun | E8: 100 | F8: 1 | G8: 4
A9: Netrunner | B9: System Restore | C9: 18 | D9: heal_percent | E9: 40 | F9: 0 | G9: 5
A10: Samurai | B10: Wired Reflexes | C10: 3 | D10: double_hit | E10: 0 | F10: 0 | G10: 3
A11: Samurai | B11: Mono-Edge Slash | C11: 7 | D11: damage_dot | E11: 130 | F11: 3 | G11: 4
A12: Samurai | B12: Subdermal Shield | C12: 12 | D12: shield | E12: 0 | F12: 1 | G12: 5
A13: Samurai | B13: Adrenaline Surge | C13: 18 | D13: mega_strike | E13: 300 | F13: 0 | G13: 6
... A17: Chrome Dealer | B17: Chrome Overcharge | C17: 18 | D17: buff_all | E17: 50 | F17: 3 | G17: 6

Sheet Dashboard
A1: ⚡ HEROES ECONOMY — BALANCE DASHBOARD | P1: Niveau | Q1: HP Joueur | R1: ATK Joueur | S1: HP Ennemi Max (Tier) | T1: ATK Ennemi Max (Tier) | V1: Niveau | W1: HP Joueur | X1: HP Ennemi Max | Z1: Niveau | AA1: ATK Joueur | AB1: ATK Ennemi Max | AD1: Rareté | AE1: Prix Min | AF1: Prix Max
A2: Analyse d'équilibrage : Combat • Économie • Progression • Loot | P2: 1 | Q2: =INDEX('Progression Niveaux'!D:D,MATCH(P2,'Progression Niveaux'!A:A,0)) -> 100 | R2: =INDEX('Progression Niveaux'!E:E,MATCH(P2,'Progression Niveaux'!A:A,0)) -> 10 | S2: =_xlfn.MAXIFS(Ennemis!C:C,Ennemis!B:B,1) -> 50 | T2: =_xlfn.MAXIFS(Ennemis!D:D,Ennemis!B:B,1) -> 8 | V2: 1 | W2: =Q2 -> 100 | X2: =S2 -> 50 | Z2: 1 | AA2: =R2 -> 10 | AB2: =T2 -> 8 | AD2: Common | AE2: =I7 -> 80 | AF2: =J7 -> 50000
P3: 3 | Q3: =INDEX('Progression Niveaux'!D:D,MATCH(P3,'Progression Niveaux'!A:A,0)) -> 123 | R3: =INDEX('Progression Niveaux'!E:E,MATCH(P3,'Progression Niveaux'!A:A,0)) -> 14 | S3: =_xlfn.MAXIFS(Ennemis!C:C,Ennemis!B:B,2) -> 80 | T3: =_xlfn.MAXIFS(Ennemis!D:D,Ennemis!B:B,2) -> 20 | V3: 3 | W3: =Q3 -> 123 | X3: =S3 -> 80 | Z3: 3 | AA3: =R3 -> 14 | AB3: =T3 -> 20 | AD3: Uncommon | AE3: =I8 -> 300 | AF3: =J8 -> 500000
A4: 📦 ITEMS PAR RARETÉ & TYPE | H4: 💰 PRIX MOYEN PAR RARETÉ | P4: 5 | Q4: =INDEX('Progression Niveaux'!D:D,MATCH(P4,'Progression Niveaux'!A:A,0)) -> 152 | R4: =INDEX('Progression Niveaux'!E:E,MATCH(P4,'Progression Niveaux'!A:A,0)) -> 19 | S4: =_xlfn.MAXIFS(Ennemis!C:C,Ennemis!B:B,2) -> 80 | T4: =_xlfn.MAXIFS(Ennemis!D:D,Ennemis!B:B,2) -> 20 | V4: 5 | W4: =Q4 -> 152 | X4: =S4 -> 80 | Z4: 5 | AA4: =R4 -> 19 | AB4: =T4 -> 20 | AD4: Rare | AE4: =I9 -> 4000 | AF4: =J9 -> 5000000
A5: Rareté | B5: Weapons | C5: Armors | D5: Implants | E5: Autres | F5: Total | H5: Rareté | I5: Prix Min | J5: Prix Max | K5: Prix Moyen | P5: 8 | Q5: =INDEX('Progression Niveaux'!D:D,MATCH(P5,'Progression Niveaux'!A:A,0)) -> 207 | R5: =INDEX('Progression Niveaux'!E:E,MATCH(P5,'Progression Niveaux'!A:A,0)) -> 28 | S5: =_xlfn.MAXIFS(Ennemis!C:C,Ennemis!B:B,3) -> 200 | T5: =_xlfn.MAXIFS(Ennemis!D:D,Ennemis!B:B,3) -> 35 | V5: 8 | W5: =Q5 -> 207 | X5: =S5 -> 200 | Z5: 8 | AA5: =R5 -> 28 | AB5: =T5 -> 35 | AD5: Epic | AE5: =I10 -> 18000 | AF5: =J10 -> 320000
A6: Common | B6: =COUNTIFS(Items!B:B,"weapon",Items!C:C,"common") -> 3 | C6: =COUNTIFS(Items!B:B,"armor",Items!C:C,"common") -> 2 | D6: =COUNTIFS(Items!B:B,"implant",Items!C:C,"common") -> 2 | E6: =COUNTIFS(Items!C:C,"common")-B6-C6-D6 -> 6 | F6: =SUM(B6:E6) -> 13 | H6: Common | I6: =_xlfn.MINIFS(Items!D:D,Items!C:C,"common") -> 25 | J6: =_xlfn.MAXIFS(Items!D:D,Items!C:C,"common") -> 5000 | K6: =AVERAGEIFS(Items!D:D,Items!C:C,"common") -> 915.76923 | P6: 10 | Q6: =INDEX('Progression Niveaux'!D:D,MATCH(P6,'Progression Niveaux'!A:A,0)) -> 251 | R6: =INDEX('Progression Niveaux'!E:E,MATCH(P6,'Progression Niveaux'!A:A,0)) -> 35 | S6: =_xlfn.MAXIFS(Ennemis!C:C,Ennemis!B:B,3) -> 200 | T6: =_xlfn.MAXIFS(Ennemis!D:D,Ennemis!B:B,3) -> 35 | V6: 10 | W6: =Q6 -> 251 | X6: =S6 -> 200 | Z6: 10 | AA6: =R6 -> 35 | AB6: =T6 -> 35 | AD6: Legendary | AE6: =I11 -> 0 | AF6: =J11 -> 0
A7: Uncommon | B7: =COUNTIFS(Items!B:B,"weapon",Items!C:C,"uncommon") -> 2 | C7: =COUNTIFS(Items!B:B,"armor",Items!C:C,"uncommon") -> 2 | D7: =COUNTIFS(Items!B:B,"implant",Items!C:C,"uncommon") -> 2 | E7: =COUNTIFS(Items!C:C,"uncommon")-B7-C7-D7 -> 6 | F7: =SUM(B7:E7) -> 12 | H7: Uncommon | I7: =_xlfn.MINIFS(Items!D:D,Items!C:C,"uncommon") -> 80 | J7: =_xlfn.MAXIFS(Items!D:D,Items!C:C,"uncommon") -> 50000 | K7: =AVERAGEIFS(Items!D:D,Items!C:C,"uncommon") -> 5485.8333 | P7: 15 | Q7: =INDEX('Progression Niveaux'!D:D,MATCH(P7,'Progression Niveaux'!A:A,0)) -> 387 | R7: =INDEX('Progression Niveaux'!E:E,MATCH(P7,'Progression Niveaux'!A:A,0)) -> 56 | S7: =_xlfn.MAXIFS(Ennemis!C:C,Ennemis!B:B,4) -> 1200 | T7: =_xlfn.MAXIFS(Ennemis!D:D,Ennemis!B:B,4) -> 80 | V7: 15 | W7: =Q7 -> 387 | X7: =S7 -> 1200 | Z7: 15 | AA7: =R7 -> 56 | AB7: =T7 -> 80
A8: Rare | B8: =COUNTIFS(Items!B:B,"weapon",Items!C:C,"rare") -> 2 | C8: =COUNTIFS(Items!B:B,"armor",Items!C:C,"rare") -> 2 | D8: =COUNTIFS(Items!B:B,"implant",Items!C:C,"rare") -> 2 | E8: =COUNTIFS(Items!C:C,"rare")-B8-C8-D8 -> 7 | F8: =SUM(B8:E8) -> 13 | H8: Rare | I8: =_xlfn.MINIFS(Items!D:D,Items!C:C,"rare") -> 300 | J8: =_xlfn.MAXIFS(Items!D:D,Items!C:C,"rare") -> 500000 | K8: =AVERAGEIFS(Items!D:D,Items!C:C,"rare") -> 44061.538 | P8: 20 | Q8: =INDEX('Progression Niveaux'!D:D,MATCH(P8,'Progression Niveaux'!A:A,0)) -> 561 | R8: =INDEX('Progression Niveaux'!E:E,MATCH(P8,'Progression Niveaux'!A:A,0)) -> 82 | S8: =_xlfn.MAXIFS(Ennemis!C:C,Ennemis!B:B,5) -> 2600 | T8: =_xlfn.MAXIFS(Ennemis!D:D,Ennemis!B:B,5) -> 135 | V8: 20 | W8: =Q8 -> 561 | X8: =S8 -> 2600 | Z8: 20 | AA8: =R8 -> 82 | AB8: =T8 -> 135
A9: Epic | B9: =COUNTIFS(Items!B:B,"weapon",Items!C:C,"epic") -> 2 | C9: =COUNTIFS(Items!B:B,"armor",Items!C:C,"epic") -> 2 | D9: =COUNTIFS(Items!B:B,"implant",Items!C:C,"epic") -> 2 | E9: =COUNTIFS(Items!C:C,"epic")-B9-C9-D9 -> 5 | F9: =SUM(B9:E9) -> 11 | H9: Epic | I9: =_xlfn.MINIFS(Items!D:D,Items!C:C,"epic") -> 4000 | J9: =_xlfn.MAXIFS(Items!D:D,Items!C:C,"epic") -> 5000000 | K9: =AVERAGEIFS(Items!D:D,Items!C:C,"epic") -> 480318.18 | P9: 24 | Q9: =INDEX('Progression Niveaux'!D:D,MATCH(P9,'Progression Niveaux'!A:A,0)) -> 727 | R9: =INDEX('Progression Niveaux'!E:E,MATCH(P9,'Progression Niveaux'!A:A,0)) -> 106 | S9: =_xlfn.MAXIFS(Ennemis!C:C,Ennemis!B:B,5) -> 2600 | T9: =_xlfn.MAXIFS(Ennemis!D:D,Ennemis!B:B,5) -> 135 | V9: 24 | W9: =Q9 -> 727 | X9: =S9 -> 2600 | Z9: 24 | AA9: =R9 -> 106 | AB9: =T9 -> 135
A10: Legendary | B10: =COUNTIFS(Items!B:B,"weapon",Items!C:C,"legendary") -> 2 | C10: =COUNTIFS(Items!B:B,"armor",Items!C:C,"legendary") -> 2 | D10: =COUNTIFS(Items!B:B,"implant",Items!C:C,"legendary") -> 3 | E10: =COUNTIFS(Items!C:C,"legendary")-B10-C10-D10 -> 2 | F10: =SUM(B10:E10) -> 9 | H10: Legendary | I10: =_xlfn.MINIFS(Items!D:D,Items!C:C,"legendary") -> 18000 | J10: =_xlfn.MAXIFS(Items!D:D,Items!C:C,"legendary") -> 320000 | K10: =AVERAGEIFS(Items!D:D,Items!C:C,"legendary") -> 135000 | P10: 29 | Q10: =INDEX('Progression Niveaux'!D:D,MATCH(P10,'Progression Niveaux'!A:A,0)) -> 968 | R10: =INDEX('Progression Niveaux'!E:E,MATCH(P10,'Progression Niveaux'!A:A,0)) -> 141 | S10: =_xlfn.MAXIFS(Ennemis!C:C,Ennemis!B:B,6) -> 4700 | T10: =_xlfn.MAXIFS(Ennemis!D:D,Ennemis!B:B,6) -> 195 | V10: 29 | W10: =Q10 -> 968 | X10: =S10 -> 4700 | Z10: 29 | AA10: =R10 -> 141 | AB10: =T10 -> 195
A11: TOTAL | B11: =SUM(B6:B10) -> 11 | C11: =SUM(C6:C10) -> 10 | D11: =SUM(D6:D10) -> 11 | E11: =SUM(E6:E10) -> 26 | F11: =SUM(F6:F10) -> 58 | P11: 34 | Q11: =INDEX('Progression Niveaux'!D:D,MATCH(P11,'Progression Niveaux'!A:A,0)) -> 1247 | R11: =INDEX('Progression Niveaux'!E:E,MATCH(P11,'Progression Niveaux'!A:A,0)) -> 181 | S11: =_xlfn.MAXIFS(Ennemis!C:C,Ennemis!B:B,6) -> 4700 | T11: =_xlfn.MAXIFS(Ennemis!D:D,Ennemis!B:B,6) -> 195 | V11: 34 | W11: =Q11 -> 1247 | X11: =S11 -> 4700 | Z11: 34 | AA11: =R11 -> 181 | AB11: =T11 -> 195
P12: 40 | Q12: =INDEX('Progression Niveaux'!D:D,MATCH(P12,'Progression Niveaux'!A:A,0)) -> 1631 | R12: =INDEX('Progression Niveaux'!E:E,MATCH(P12,'Progression Niveaux'!A:A,0)) -> 236 | S12: =_xlfn.MAXIFS(Ennemis!C:C,Ennemis!B:B,7) -> 9800 | T12: =_xlfn.MAXIFS(Ennemis!D:D,Ennemis!B:B,7) -> 285 | V12: 40 | W12: =Q12 -> 1631 | X12: =S12 -> 9800 | Z12: 40 | AA12: =R12 -> 236 | AB12: =T12 -> 285
A13: ⚔️ COMBAT BALANCE — JOUEUR vs ENNEMIS | P13: 48 | Q13: =INDEX('Progression Niveaux'!D:D,MATCH(P13,'Progression Niveaux'!A:A,0)) -> 2227 | R13: =INDEX('Progression Niveaux'!E:E,MATCH(P13,'Progression Niveaux'!A:A,0)) -> 320 | S13: =_xlfn.MAXIFS(Ennemis!C:C,Ennemis!B:B,7) -> 9800 | T13: =_xlfn.MAXIFS(Ennemis!D:D,Ennemis!B:B,7) -> 285 | V13: 48 | W13: =Q13 -> 2227 | X13: =S13 -> 9800 | Z13: 48 | AA13: =R13 -> 320 | AB13: =T13 -> 285
A14: Ennemi | B14: Tier | C14: Niv. Min Donjon | D14: HP Ennemi | E14: ATK Ennemi | F14: DEF Ennemi | G14: HP Joueur @Niv | H14: ATK Joueur @Niv | I14: DEF Joueur @Niv | J14: Ratio HP (Joueur/Ennemi) | K14: Ratio ATK (J/E) | L14: Ratio DEF (J/E) | M14: Coups pour tuer ennemi | N14: ⚠️ Équilibré? | P14: 60 | Q14: =INDEX('Progression Niveaux'!D:D,MATCH(P14,'Progression Niveaux'!A:A,0)) -> 3301 | R14: =INDEX('Progression Niveaux'!E:E,MATCH(P14,'Progression Niveaux'!A:A,0)) -> 470 | S14: =_xlfn.MAXIFS(Ennemis!C:C,Ennemis!B:B,7) -> 9800 | T14: =_xlfn.MAXIFS(Ennemis!D:D,Ennemis!B:B,7) -> 285 | V14: 60 | W14: =Q14 -> 3301 | X14: =S14 -> 9800 | Z14: 60 | AA14: =R14 -> 470 | AB14: =T14 -> 285
A15: Glitched Drone | B15: 1 | C15: 1 | D15: =INDEX(Ennemis!C:C,MATCH(A15,Ennemis!A:A,0)) -> 30 | E15: =INDEX(Ennemis!D:D,MATCH(A15,Ennemis!A:A,0)) -> 5 | F15: =INDEX(Ennemis!E:E,MATCH(A15,Ennemis!A:A,0)) -> 2 | G15: =INDEX('Progression Niveaux'!D:D,MATCH(C15,'Progression Niveaux'!A:A,0)) -> 100 | H15: =INDEX('Progression Niveaux'!E:E,MATCH(C15,'Progression Niveaux'!A:A,0)) -> 10 | I15: =INDEX('Progression Niveaux'!F:F,MATCH(C15,'Progression Niveaux'!A:A,0)) -> 5 | J15: =G15/D15 -> 3.3333333 | K15: =H15/E15 -> 2 | L15: =I15/F15 -> 2.5 | M15: =ROUNDUP(D15/MAX(H15-F15,1),0) -> 4 | N15: =IF(AND(J15>=0.3,J15<=5,M15>=2,M15<=30),"✅ OK","⚠️ CHECK") -> ✅ OK | P15: 80 | Q15: =INDEX('Progression Niveaux'!D:D,MATCH(P15,'Progression Niveaux'!A:A,0)) -> 5571 | R15: =INDEX('Progression Niveaux'!E:E,MATCH(P15,'Progression Niveaux'!A:A,0)) -> 784 | S15: =_xlfn.MAXIFS(Ennemis!C:C,Ennemis!B:B,7) -> 9800 | T15: =_xlfn.MAXIFS(Ennemis!D:D,Ennemis!B:B,7) -> 285 | V15: 80 | W15: =Q15 -> 5571 | X15: =S15 -> 9800 | Z15: 80 | AA15: =R15 -> 784 | AB15: =T15 -> 285
A16: Neon Rat | B16: 1 | C16: 1 | D16: =INDEX(Ennemis!C:C,MATCH(A16,Ennemis!A:A,0)) -> 20 | E16: =INDEX(Ennemis!D:D,MATCH(A16,Ennemis!A:A,0)) -> 8 | F16: =INDEX(Ennemis!E:E,MATCH(A16,Ennemis!A:A,0)) -> 1 | G16: =INDEX('Progression Niveaux'!D:D,MATCH(C16,'Progression Niveaux'!A:A,0)) -> 100 | H16: =INDEX('Progression Niveaux'!E:E,MATCH(C16,'Progression Niveaux'!A:A,0)) -> 10 | I16: =INDEX('Progression Niveaux'!F:F,MATCH(C16,'Progression Niveaux'!A:A,0)) -> 5 | J16: =G16/D16 -> 5 | K16: =H16/E16 -> 1.25 | L16: =I16/F16 -> 5 | M16: =ROUNDUP(D16/MAX(H16-F16,1),0) -> 3 | N16: =IF(AND(J16>=0.3,J16<=5,M16>=2,M16<=30),"✅ OK","⚠️ CHECK") -> ✅ OK | P16: 100 | Q16: =INDEX('Progression Niveaux'!D:D,MATCH(P16,'Progression Niveaux'!A:A,0)) -> 8441 | R16: =INDEX('Progression Niveaux'!E:E,MATCH(P16,'Progression Niveaux'!A:A,0)) -> 1178 | S16: =_xlfn.MAXIFS(Ennemis!C:C,Ennemis!B:B,7) -> 9800 | T16: =_xlfn.MAXIFS(Ennemis!D:D,Ennemis!B:B,7) -> 285 | V16: 100 | W16: =Q16 -> 8441 | X16: =S16 -> 9800 | Z16: 100 | AA16: =R16 -> 1178 | AB16: =T16 -> 285
A17: Street Thug | B17: 1 | C17: 1 | D17: =INDEX(Ennemis!C:C,MATCH(A17,Ennemis!A:A,0)) -> 50 | E17: =INDEX(Ennemis!D:D,MATCH(A17,Ennemis!A:A,0)) -> 7 | F17: =INDEX(Ennemis!E:E,MATCH(A17,Ennemis!A:A,0)) -> 3 | G17: =INDEX('Progression Niveaux'!D:D,MATCH(C17,'Progression Niveaux'!A:A,0)) -> 100 | H17: =INDEX('Progression Niveaux'!E:E,MATCH(C17,'Progression Niveaux'!A:A,0)) -> 10 | I17: =INDEX('Progression Niveaux'!F:F,MATCH(C17,'Progression Niveaux'!A:A,0)) -> 5 | J17: =G17/D17 -> 2 | K17: =H17/E17 -> 1.4285714 | L17: =I17/F17 -> 1.6666667 | M17: =ROUNDUP(D17/MAX(H17-F17,1),0) -> 8 | N17: =IF(AND(J17>=0.3,J17<=5,M17>=2,M17<=30),"✅ OK","⚠️ CHECK") -> ✅ OK | P17: 120 | Q17: =INDEX('Progression Niveaux'!D:D,MATCH(P17,'Progression Niveaux'!A:A,0)) -> 11911 | R17: =INDEX('Progression Niveaux'!E:E,MATCH(P17,'Progression Niveaux'!A:A,0)) -> 1652 | S17: =_xlfn.MAXIFS(Ennemis!C:C,Ennemis!B:B,7) -> 9800 | T17: =_xlfn.MAXIFS(Ennemis!D:D,Ennemis!B:B,7) -> 285 | V17: 120 | W17: =Q17 -> 11911 | X17: =S17 -> 9800 | Z17: 120 | AA17: =R17 -> 1652 | AB17: =T17 -> 285
A18: Rogue AI Drone | B18: 2 | C18: 3 | D18: =INDEX(Ennemis!C:C,MATCH(A18,Ennemis!A:A,0)) -> 80 | E18: =INDEX(Ennemis!D:D,MATCH(A18,Ennemis!A:A,0)) -> 15 | F18: =INDEX(Ennemis!E:E,MATCH(A18,Ennemis!A:A,0)) -> 8 | G18: =INDEX('Progression Niveaux'!D:D,MATCH(C18,'Progression Niveaux'!A:A,0)) -> 123 | H18: =INDEX('Progression Niveaux'!E:E,MATCH(C18,'Progression Niveaux'!A:A,0)) -> 14 | I18: =INDEX('Progression Niveaux'!F:F,MATCH(C18,'Progression Niveaux'!A:A,0)) -> 7 | J18: =G18/D18 -> 1.5375 | K18: =H18/E18 -> 0.93333333 | L18: =I18/F18 -> 0.875 | M18: =ROUNDUP(D18/MAX(H18-F18,1),0) -> 14 | N18: =IF(AND(J18>=0.3,J18<=5,M18>=2,M18<=30),"✅ OK","⚠️ CHECK") -> ✅ OK | P18: 150 | Q18: =INDEX('Progression Niveaux'!D:D,MATCH(P18,'Progression Niveaux'!A:A,0)) -> 18241 | R18: =INDEX('Progression Niveaux'!E:E,MATCH(P18,'Progression Niveaux'!A:A,0)) -> 2513 | S18: =_xlfn.MAXIFS(Ennemis!C:C,Ennemis!B:B,7) -> 9800 | T18: =_xlfn.MAXIFS(Ennemis!D:D,Ennemis!B:B,7) -> 285 | V18: 150 | W18: =Q18 -> 18241 | X18: =S18 -> 9800 | Z18: 150 | AA18: =R18 -> 2513 | AB18: =T18 -> 285
A19: Cyber Jackal | B19: 2 | C19: 3 | D19: =INDEX(Ennemis!C:C,MATCH(A19,Ennemis!A:A,0)) -> 60 | E19: =INDEX(Ennemis!D:D,MATCH(A19,Ennemis!A:A,0)) -> 20 | F19: =INDEX(Ennemis!E:E,MATCH(A19,Ennemis!A:A,0)) -> 5 | G19: =INDEX('Progression Niveaux'!D:D,MATCH(C19,'Progression Niveaux'!A:A,0)) -> 123 | H19: =INDEX('Progression Niveaux'!E:E,MATCH(C19,'Progression Niveaux'!A:A,0)) -> 14 | I19: =INDEX('Progression Niveaux'!F:F,MATCH(C19,'Progression Niveaux'!A:A,0)) -> 7 | J19: =G19/D19 -> 2.05 | K19: =H19/E19 -> 0.7 | L19: =I19/F19 -> 1.4 | M19: =ROUNDUP(D19/MAX(H19-F19,1),0) -> 7 | N19: =IF(AND(J19>=0.3,J19<=5,M19>=2,M19<=30),"✅ OK","⚠️ CHECK") -> ✅ OK
A20: DataWraith | B20: 2 | C20: 3 | D20: =INDEX(Ennemis!C:C,MATCH(A20,Ennemis!A:A,0)) -> 70 | E20: =INDEX(Ennemis!D:D,MATCH(A20,Ennemis!A:A,0)) -> 18 | F20: =INDEX(Ennemis!E:E,MATCH(A20,Ennemis!A:A,0)) -> 10 | G20: =INDEX('Progression Niveaux'!D:D,MATCH(C20,'Progression Niveaux'!A:A,0)) -> 123 | H20: =INDEX('Progression Niveaux'!E:E,MATCH(C20,'Progression Niveaux'!A:A,0)) -> 14 | I20: =INDEX('Progression Niveaux'!F:F,MATCH(C20,'Progression Niveaux'!A:A,0)) -> 7 | J20: =G20/D20 -> 1.7571429 | K20: =H20/E20 -> 0.77777778 | L20: =I20/F20 -> 0.7 | M20: =ROUNDUP(D20/MAX(H20-F20,1),0) -> 18 | N20: =IF(AND(J20>=0.3,J20<=5,M20>=2,M20<=30),"✅ OK","⚠️ CHECK") -> ✅ OK
A21: Corp Security Bot | B21: 3 | C21: 8 | D21: =INDEX(Ennemis!C:C,MATCH(A21,Ennemis!A:A,0)) -> 150 | E21: =INDEX(Ennemis!D:D,MATCH(A21,Ennemis!A:A,0)) -> 25 | F21: =INDEX(Ennemis!E:E,MATCH(A21,Ennemis!A:A,0)) -> 20 | G21: =INDEX('Progression Niveaux'!D:D,MATCH(C21,'Progression Niveaux'!A:A,0)) -> 207 | H21: =INDEX('Progression Niveaux'!E:E,MATCH(C21,'Progression Niveaux'!A:A,0)) -> 28 | I21: =INDEX('Progression Niveaux'!F:F,MATCH(C21,'Progression Niveaux'!A:A,0)) -> 16 | J21: =G21/D21 -> 1.38 | K21: =H21/E21 -> 1.12 | L21: =I21/F21 -> 0.8 | M21: =ROUNDUP(D21/MAX(H21-F21,1),0) -> 19 | N21: =IF(AND(J21>=0.3,J21<=5,M21>=2,M21<=30),"✅ OK","⚠️ CHECK") -> ✅ OK
A22: Netrunner Assassin | B22: 3 | C22: 8 | D22: =INDEX(Ennemis!C:C,MATCH(A22,Ennemis!A:A,0)) -> 100 | E22: =INDEX(Ennemis!D:D,MATCH(A22,Ennemis!A:A,0)) -> 35 | F22: =INDEX(Ennemis!E:E,MATCH(A22,Ennemis!A:A,0)) -> 12 | G22: =INDEX('Progression Niveaux'!D:D,MATCH(C22,'Progression Niveaux'!A:A,0)) -> 207 | H22: =INDEX('Progression Niveaux'!E:E,MATCH(C22,'Progression Niveaux'!A:A,0)) -> 28 | I22: =INDEX('Progression Niveaux'!F:F,MATCH(C22,'Progression Niveaux'!A:A,0)) -> 16 | J22: =G22/D22 -> 2.07 | K22: =H22/E22 -> 0.8 | L22: =I22/F22 -> 1.3333333 | M22: =ROUNDUP(D22/MAX(H22-F22,1),0) -> 7 | N22: =IF(AND(J22>=0.3,J22<=5,M22>=2,M22<=30),"✅ OK","⚠️ CHECK") -> ✅ OK
A23: Mech Walker | B23: 3 | C23: 8 | D23: =INDEX(Ennemis!C:C,MATCH(A23,Ennemis!A:A,0)) -> 200 | E23: =INDEX(Ennemis!D:D,MATCH(A23,Ennemis!A:A,0)) -> 30 | F23: =INDEX(Ennemis!E:E,MATCH(A23,Ennemis!A:A,0)) -> 25 | G23: =INDEX('Progression Niveaux'!D:D,MATCH(C23,'Progression Niveaux'!A:A,0)) -> 207 | H23: =INDEX('Progression Niveaux'!E:E,MATCH(C23,'Progression Niveaux'!A:A,0)) -> 28 | I23: =INDEX('Progression Niveaux'!F:F,MATCH(C23,'Progression Niveaux'!A:A,0)) -> 16 | J23: =G23/D23 -> 1.035 | K23: =H23/E23 -> 0.93333333 | L23: =I23/F23 -> 0.64 | M23: =ROUNDUP(D23/MAX(H23-F23,1),0) -> 67 | N23: =IF(AND(J23>=0.3,J23<=5,M23>=2,M23<=30),"✅ OK","⚠️ CHECK") -> ⚠️ CHECK
A24: ARCHON | B24: 4 | C24: 15 | D24: =INDEX(Ennemis!C:C,MATCH(A24,Ennemis!A:A,0)) -> 500 | E24: =INDEX(Ennemis!D:D,MATCH(A24,Ennemis!A:A,0)) -> 50 | F24: =INDEX(Ennemis!E:E,MATCH(A24,Ennemis!A:A,0)) -> 30 | G24: =INDEX('Progression Niveaux'!D:D,MATCH(C24,'Progression Niveaux'!A:A,0)) -> 387 | H24: =INDEX('Progression Niveaux'!E:E,MATCH(C24,'Progression Niveaux'!A:A,0)) -> 56 | I24: =INDEX('Progression Niveaux'!F:F,MATCH(C24,'Progression Niveaux'!A:A,0)) -> 37 | J24: =G24/D24 -> 0.774 | K24: =H24/E24 -> 1.12 | L24: =I24/F24 -> 1.2333333 | M24: =ROUNDUP(D24/MAX(H24-F24,1),0) -> 20 | N24: =IF(AND(J24>=0.3,J24<=5,M24>=2,M24<=30),"✅ OK","⚠️ CHECK") -> ✅ OK
A25: Chrome Dragon | B25: 4 | C25: 15 | D25: =INDEX(Ennemis!C:C,MATCH(A25,Ennemis!A:A,0)) -> 800 | E25: =INDEX(Ennemis!D:D,MATCH(A25,Ennemis!A:A,0)) -> 60 | F25: =INDEX(Ennemis!E:E,MATCH(A25,Ennemis!A:A,0)) -> 40 | G25: =INDEX('Progression Niveaux'!D:D,MATCH(C25,'Progression Niveaux'!A:A,0)) -> 387 | H25: =INDEX('Progression Niveaux'!E:E,MATCH(C25,'Progression Niveaux'!A:A,0)) -> 56 | I25: =INDEX('Progression Niveaux'!F:F,MATCH(C25,'Progression Niveaux'!A:A,0)) -> 37 | J25: =G25/D25 -> 0.48375 | K25: =H25/E25 -> 0.93333333 | L25: =I25/F25 -> 0.925 | M25: =ROUNDUP(D25/MAX(H25-F25,1),0) -> 50 | N25: =IF(AND(J25>=0.3,J25<=5,M25>=2,M25<=30),"✅ OK","⚠️ CHECK") -> ⚠️ CHECK
A26: The Void King | B26: 4 | C26: 15 | D26: =INDEX(Ennemis!C:C,MATCH(A26,Ennemis!A:A,0)) -> 1200 | E26: =INDEX(Ennemis!D:D,MATCH(A26,Ennemis!A:A,0)) -> 80 | F26: =INDEX(Ennemis!E:E,MATCH(A26,Ennemis!A:A,0)) -> 50 | G26: =INDEX('Progression Niveaux'!D:D,MATCH(C26,'Progression Niveaux'!A:A,0)) -> 387 | H26: =INDEX('Progression Niveaux'!E:E,MATCH(C26,'Progression Niveaux'!A:A,0)) -> 56 | I26: =INDEX('Progression Niveaux'!F:F,MATCH(C26,'Progression Niveaux'!A:A,0)) -> 37 | J26: =G26/D26 -> 0.3225 | K26: =H26/E26 -> 0.7 | L26: =I26/F26 -> 0.74 | M26: =ROUNDUP(D26/MAX(H26-F26,1),0) -> 200 | N26: =IF(AND(J26>=0.3,J26<=5,M26>=2,M26<=30),"✅ OK","⚠️ CHECK") -> ⚠️ CHECK
A27: Black ICE Hound | B27: 5 | C27: 20 | D27: =INDEX(Ennemis!C:C,MATCH(A27,Ennemis!A:A,0)) -> 1800 | E27: =INDEX(Ennemis!D:D,MATCH(A27,Ennemis!A:A,0)) -> 110 | F27: =INDEX(Ennemis!E:E,MATCH(A27,Ennemis!A:A,0)) -> 75 | G27: =INDEX('Progression Niveaux'!D:D,MATCH(C27,'Progression Niveaux'!A:A,0)) -> 561 | H27: =INDEX('Progression Niveaux'!E:E,MATCH(C27,'Progression Niveaux'!A:A,0)) -> 82 | I27: =INDEX('Progression Niveaux'!F:F,MATCH(C27,'Progression Niveaux'!A:A,0)) -> 58 | J27: =G27/D27 -> 0.31166667 | K27: =H27/E27 -> 0.74545455 | L27: =I27/F27 -> 0.77333333 | M27: =ROUNDUP(D27/MAX(H27-F27,1),0) -> 258 | N27: =IF(AND(J27>=0.3,J27<=5,M27>=2,M27<=30),"✅ OK","⚠️ CHECK") -> ⚠️ CHECK
A28: Maelstrom Ripper | B28: 5 | C28: 20 | D28: =INDEX(Ennemis!C:C,MATCH(A28,Ennemis!A:A,0)) -> 2200 | E28: =INDEX(Ennemis!D:D,MATCH(A28,Ennemis!A:A,0)) -> 125 | F28: =INDEX(Ennemis!E:E,MATCH(A28,Ennemis!A:A,0)) -> 85 | G28: =INDEX('Progression Niveaux'!D:D,MATCH(C28,'Progression Niveaux'!A:A,0)) -> 561 | H28: =INDEX('Progression Niveaux'!E:E,MATCH(C28,'Progression Niveaux'!A:A,0)) -> 82 | I28: =INDEX('Progression Niveaux'!F:F,MATCH(C28,'Progression Niveaux'!A:A,0)) -> 58 | J28: =G28/D28 -> 0.255 | K28: =H28/E28 -> 0.656 | L28: =I28/F28 -> 0.68235294 | M28: =ROUNDUP(D28/MAX(H28-F28,1),0) -> 2200 | N28: =IF(AND(J28>=0.3,J28<=5,M28>=2,M28<=30),"✅ OK","⚠️ CHECK") -> ⚠️ CHECK
A29: Militech Suppressor | B29: 5 | C29: 20 | D29: =INDEX(Ennemis!C:C,MATCH(A29,Ennemis!A:A,0)) -> 2600 | E29: =INDEX(Ennemis!D:D,MATCH(A29,Ennemis!A:A,0)) -> 135 | F29: =INDEX(Ennemis!E:E,MATCH(A29,Ennemis!A:A,0)) -> 95 | G29: =INDEX('Progression Niveaux'!D:D,MATCH(C29,'Progression Niveaux'!A:A,0)) -> 561 | H29: =INDEX('Progression Niveaux'!E:E,MATCH(C29,'Progression Niveaux'!A:A,0)) -> 82 | I29: =INDEX('Progression Niveaux'!F:F,MATCH(C29,'Progression Niveaux'!A:A,0)) -> 58 | J29: =G29/D29 -> 0.21576923 | K29: =H29/E29 -> 0.60740741 | L29: =I29/F29 -> 0.61052632 | M29: =ROUNDUP(D29/MAX(H29-F29,1),0) -> 2600 | N29: =IF(AND(J29>=0.3,J29<=5,M29>=2,M29<=30),"✅ OK","⚠️ CHECK") -> ⚠️ CHECK
A30: Arasaka Counter-Intel | B30: 6 | C30: 29 | D30: =INDEX(Ennemis!C:C,MATCH(A30,Ennemis!A:A,0)) -> 3200 | E30: =INDEX(Ennemis!D:D,MATCH(A30,Ennemis!A:A,0)) -> 155 | F30: =INDEX(Ennemis!E:E,MATCH(A30,Ennemis!A:A,0)) -> 110 | G30: =INDEX('Progression Niveaux'!D:D,MATCH(C30,'Progression Niveaux'!A:A,0)) -> 968 | H30: =INDEX('Progression Niveaux'!E:E,MATCH(C30,'Progression Niveaux'!A:A,0)) -> 141 | I30: =INDEX('Progression Niveaux'!F:F,MATCH(C30,'Progression Niveaux'!A:A,0)) -> 108 | J30: =G30/D30 -> 0.3025 | K30: =H30/E30 -> 0.90967742 | L30: =I30/F30 -> 0.98181818 | M30: =ROUNDUP(D30/MAX(H30-F30,1),0) -> 104 | N30: =IF(AND(J30>=0.3,J30<=5,M30>=2,M30<=30),"✅ OK","⚠️ CHECK") -> ⚠️ CHECK
... A36: Soulkiller Prime | B36: 7 | C36: 40 | D36: =INDEX(Ennemis!C:C,MATCH(A36,Ennemis!A:A,0)) -> 9800 | E36: =INDEX(Ennemis!D:D,MATCH(A36,Ennemis!A:A,0)) -> 285 | F36: =INDEX(Ennemis!E:E,MATCH(A36,Ennemis!A:A,0)) -> 220 | G36: =INDEX('Progression Niveaux'!D:D,MATCH(C36,'Progression Niveaux'!A:A,0)) -> 1631 | H36: =INDEX('Progression Niveaux'!E:E,MATCH(C36,'Progression Niveaux'!A:A,0)) -> 236 | I36: =INDEX('Progression Niveaux'!F:F,MATCH(C36,'Progression Niveaux'!A:A,0)) -> 192 | J36: =G36/D36 -> 0.16642857 | K36: =H36/E36 -> 0.82807018 | L36: =I36/F36 -> 0.87272727 | M36: =ROUNDUP(D36/MAX(H36-F36,1),0) -> 613 | N36: =IF(AND(J36>=0.3,J36<=5,M36>=2,M36<=30),"✅ OK","⚠️ CHECK") -> ⚠️ CHECK
A39: 💰 ÉCONOMIE — REVENUS vs COÛTS D'ÉQUIPEMENT
A40: Tier Ennemi | B40: Crédits Moy/Kill | C40: Meilleure Arme Tier | D40: Prix Arme | E40: Meilleure Armure Tier | F40: Prix Armure | G40: Meilleur Implant Tier | H40: Prix Implant | I40: Coût Total Équip | J40: Kills pour équip | K40: XP Moy/Kill | L40: Heures estimées
A41: Tier 1 | B41: =(AVERAGEIFS(Ennemis!G:G,Ennemis!B:B,1)+AVERAGEIFS(Ennemis!H:H,Ennemis!B:B,1))/2 -> 11.333333 | C41: =INDEX(Items!A:A,MATCH(_xlfn.MAXIFS(Items!D:D,Items!B:B,"weapon",Items!C:C,"common"),Items!D:D,0)) -> Budget Arms Unity+ | D41: =_xlfn.MAXIFS(Items!D:D,Items!B:B,"weapon",Items!C:C,"common") -> 350 | E41: =INDEX(Items!A:A,MATCH(_xlfn.MAXIFS(Items!D:D,Items!B:B,"armor",Items!C:C,"common"),Items!D:D,0)) -> Tyger Claws Reinforced Coat | F41: =_xlfn.MAXIFS(Items!D:D,Items!B:B,"armor",Items!C:C,"common") -> 300 | G41: =INDEX(Items!A:A,MATCH(_xlfn.MAXIFS(Items!D:D,Items!B:B,"implant",Items!C:C,"common"),Items!D:D,0)) -> Nanoweave Jacket | H41: =_xlfn.MAXIFS(Items!D:D,Items!B:B,"implant",Items!C:C,"common") -> 400 | I41: =D41+F41+H41 -> 1050 | J41: =ROUNDUP(I41/B41,0) -> 93 | K41: =AVERAGEIFS(Ennemis!F:F,Ennemis!B:B,1) -> 11 | L41: =ROUND(J41/60,1) -> 1.6
A42: Tier 2 | B42: =(AVERAGEIFS(Ennemis!G:G,Ennemis!B:B,2)+AVERAGEIFS(Ennemis!H:H,Ennemis!B:B,2))/2 -> 35 | C42: =INDEX(Items!A:A,MATCH(_xlfn.MAXIFS(Items!D:D,Items!B:B,"weapon",Items!C:C,"uncommon"),Items!D:D,0)) -> Kang Tao Shock Carbine | D42: =_xlfn.MAXIFS(Items!D:D,Items!B:B,"weapon",Items!C:C,"uncommon") -> 1400 | E42: =INDEX(Items!A:A,MATCH(_xlfn.MAXIFS(Items!D:D,Items!B:B,"armor",Items!C:C,"uncommon"),Items!D:D,0)) -> Trauma Team Ballistic Mesh | F42: =_xlfn.MAXIFS(Items!D:D,Items!B:B,"armor",Items!C:C,"uncommon") -> 1250 | G42: =INDEX(Items!A:A,MATCH(_xlfn.MAXIFS(Items!D:D,Items!B:B,"implant",Items!C:C,"uncommon"),Items!D:D,0)) -> Sandevistan Lite | H42: =_xlfn.MAXIFS(Items!D:D,Items!B:B,"implant",Items!C:C,"uncommon") -> 1600 | I42: =D42+F42+H42 -> 4250 | J42: =ROUNDUP(I42/B42,0) -> 122 | K42: =AVERAGEIFS(Ennemis!F:F,Ennemis!B:B,2) -> 30 | L42: =ROUND(J42/60,1) -> 2
A43: Tier 3 | B43: =(AVERAGEIFS(Ennemis!G:G,Ennemis!B:B,3)+AVERAGEIFS(Ennemis!H:H,Ennemis!B:B,3))/2 -> 110 | C43: =INDEX(Items!A:A,MATCH(_xlfn.MAXIFS(Items!D:D,Items!B:B,"weapon",Items!C:C,"rare"),Items!D:D,0)) -> Militech Crusher Custom | D43: =_xlfn.MAXIFS(Items!D:D,Items!B:B,"weapon",Items!C:C,"rare") -> 8500 | E43: =INDEX(Items!A:A,MATCH(_xlfn.MAXIFS(Items!D:D,Items!B:B,"armor",Items!C:C,"rare"),Items!D:D,0)) -> Militech Bastion Frame | F43: =_xlfn.MAXIFS(Items!D:D,Items!B:B,"armor",Items!C:C,"rare") -> 7800 | G43: =INDEX(Items!A:A,MATCH(_xlfn.MAXIFS(Items!D:D,Items!B:B,"implant",Items!C:C,"rare"),Items!D:D,0)) -> QianT Synapse Rail | H43: =_xlfn.MAXIFS(Items!D:D,Items!B:B,"implant",Items!C:C,"rare") -> 9200 | I43: =D43+F43+H43 -> 25500 | J43: =ROUNDUP(I43/B43,0) -> 232 | K43: =AVERAGEIFS(Ennemis!F:F,Ennemis!B:B,3) -> 70 | L43: =ROUND(J43/60,1) -> 3.9
A44: Tier 4 | B44: =(AVERAGEIFS(Ennemis!G:G,Ennemis!B:B,4)+AVERAGEIFS(Ennemis!H:H,Ennemis!B:B,4))/2 -> 1183.3333 | C44: =INDEX(Items!A:A,MATCH(_xlfn.MAXIFS(Items!D:D,Items!B:B,"weapon",Items!C:C,"rare"),Items!D:D,0)) -> Militech Crusher Custom | D44: =_xlfn.MAXIFS(Items!D:D,Items!B:B,"weapon",Items!C:C,"rare") -> 8500 | E44: =INDEX(Items!A:A,MATCH(_xlfn.MAXIFS(Items!D:D,Items!B:B,"armor",Items!C:C,"rare"),Items!D:D,0)) -> Militech Bastion Frame | F44: =_xlfn.MAXIFS(Items!D:D,Items!B:B,"armor",Items!C:C,"rare") -> 7800 | G44: =INDEX(Items!A:A,MATCH(_xlfn.MAXIFS(Items!D:D,Items!B:B,"implant",Items!C:C,"rare"),Items!D:D,0)) -> QianT Synapse Rail | H44: =_xlfn.MAXIFS(Items!D:D,Items!B:B,"implant",Items!C:C,"rare") -> 9200 | I44: =D44+F44+H44 -> 25500 | J44: =ROUNDUP(I44/B44,0) -> 22 | K44: =AVERAGEIFS(Ennemis!F:F,Ennemis!B:B,4) -> 350 | L44: =ROUND(J44/60,1) -> 0.4
A45: Tier 5 | B45: =(AVERAGEIFS(Ennemis!G:G,Ennemis!B:B,5)+AVERAGEIFS(Ennemis!H:H,Ennemis!B:B,5))/2 -> 5950 | C45: =INDEX(Items!A:A,MATCH(_xlfn.MAXIFS(Items!D:D,Items!B:B,"weapon",Items!C:C,"epic"),Items!D:D,0)) -> Arasaka Revenant Smartgun | D45: =_xlfn.MAXIFS(Items!D:D,Items!B:B,"weapon",Items!C:C,"epic") -> 52000 | E45: =INDEX(Items!A:A,MATCH(_xlfn.MAXIFS(Items!D:D,Items!B:B,"armor",Items!C:C,"epic"),Items!D:D,0)) -> Arasaka Specter Weave | F45: =_xlfn.MAXIFS(Items!D:D,Items!B:B,"armor",Items!C:C,"epic") -> 47000 | G45: =INDEX(Items!A:A,MATCH(_xlfn.MAXIFS(Items!D:D,Items!B:B,"implant",Items!C:C,"epic"),Items!D:D,0)) -> Mantis Driver Suite | H45: =_xlfn.MAXIFS(Items!D:D,Items!B:B,"implant",Items!C:C,"epic") -> 56000 | I45: =D45+F45+H45 -> 155000 | J45: =ROUNDUP(I45/B45,0) -> 27 | K45: =AVERAGEIFS(Ennemis!F:F,Ennemis!B:B,5) -> 730 | L45: =ROUND(J45/60,1) -> 0.5
A46: Tier 6 | B46: =(AVERAGEIFS(Ennemis!G:G,Ennemis!B:B,6)+AVERAGEIFS(Ennemis!H:H,Ennemis!B:B,6))/2 -> 11700 | C46: =INDEX(Items!A:A,MATCH(_xlfn.MAXIFS(Items!D:D,Items!B:B,"weapon",Items!C:C,"epic"),Items!D:D,0)) -> Arasaka Revenant Smartgun | D46: =_xlfn.MAXIFS(Items!D:D,Items!B:B,"weapon",Items!C:C,"epic") -> 52000 | E46: =INDEX(Items!A:A,MATCH(_xlfn.MAXIFS(Items!D:D,Items!B:B,"armor",Items!C:C,"epic"),Items!D:D,0)) -> Arasaka Specter Weave | F46: =_xlfn.MAXIFS(Items!D:D,Items!B:B,"armor",Items!C:C,"epic") -> 47000 | G46: =INDEX(Items!A:A,MATCH(_xlfn.MAXIFS(Items!D:D,Items!B:B,"implant",Items!C:C,"epic"),Items!D:D,0)) -> Mantis Driver Suite | H46: =_xlfn.MAXIFS(Items!D:D,Items!B:B,"implant",Items!C:C,"epic") -> 56000 | I46: =D46+F46+H46 -> 155000 | J46: =ROUNDUP(I46/B46,0) -> 14 | K46: =AVERAGEIFS(Ennemis!F:F,Ennemis!B:B,6) -> 1138.75 | L46: =ROUND(J46/60,1) -> 0.2
A47: Tier 7 | B47: =(AVERAGEIFS(Ennemis!G:G,Ennemis!B:B,7)+AVERAGEIFS(Ennemis!H:H,Ennemis!B:B,7))/2 -> 33500 | C47: =INDEX(Items!A:A,MATCH(_xlfn.MAXIFS(Items!D:D,Items!B:B,"weapon",Items!C:C,"legendary"),Items!D:D,0)) -> Blackwall Breacher | D47: =_xlfn.MAXIFS(Items!D:D,Items!B:B,"weapon",Items!C:C,"legendary") -> 240000 | E47: =INDEX(Items!A:A,MATCH(_xlfn.MAXIFS(Items!D:D,Items!B:B,"armor",Items!C:C,"legendary"),Items!D:D,0)) -> Mikoshi Nullskin | F47: =_xlfn.MAXIFS(Items!D:D,Items!B:B,"armor",Items!C:C,"legendary") -> 210000 | G47: =INDEX(Items!A:A,MATCH(_xlfn.MAXIFS(Items!D:D,Items!B:B,"implant",Items!C:C,"legendary"),Items!D:D,0)) -> Militech Apogee Sandevistan | H47: =_xlfn.MAXIFS(Items!D:D,Items!B:B,"implant",Items!C:C,"legendary") -> 320000 | I47: =D47+F47+H47 -> 770000 | J47: =ROUNDUP(I47/B47,0) -> 23 | K47: =AVERAGEIFS(Ennemis!F:F,Ennemis!B:B,7) -> 2250 | L47: =ROUND(J47/60,1) -> 0.4
A50: 🎲 LOOT VALUE — VALEUR ESPÉRÉE DES DROPS
A51: Ennemi | B51: Tier | C51: Crédits Moy/Kill | D51: Drop 1 | E51: % Drop 1 | F51: Prix Drop 1 | G51: Drop 2 | H51: % Drop 2 | I51: Prix Drop 2 | J51: Valeur Espérée Loot | K51: Valeur Totale/Kill | L51: Ratio Loot/Crédits
A52: Glitched Drone | B52: =INDEX(Ennemis!B:B,MATCH(A52,Ennemis!A:A,0)) -> 1 | C52: =(INDEX(Ennemis!G:G,MATCH(A52,Ennemis!A:A,0))+INDEX(Ennemis!H:H,MATCH(A52,Ennemis!A:A,0)))/2 -> 10 | D52: =IFERROR(INDEX('Loot Table'!B:B,MATCH(A52,'Loot Table'!A:A,0)),"-") -> Stim Pack | E52: =IFERROR(INDEX('Loot Table'!C:C,MATCH(A52,'Loot Table'!A:A,0)),0) -> 0.3 | F52: =IFERROR(INDEX(Items!D:D,MATCH(D52,Items!A:A,0)),0) -> 25 | G52: {=IFERROR(INDEX('Loot Table'!B:B,MATCH(A52,'Loot Table'!A:A,0)+1),"-")} -> Finger Servos | H52: {=IFERROR(INDEX('Loot Table'!C:C,MATCH(A52,'Loot Table'!A:A,0)+1),0)} -> 0.1 | I52: =IFERROR(INDEX(Items!D:D,MATCH(G52,Items!A:A,0)),0) -> 5000 | J52: =E52*F52+H52*I52 -> 507.5 | K52: =C52+J52 -> 517.5 | L52: =IF(C52>0,J52/C52,0) -> 50.75
A53: Street Thug | B53: =INDEX(Ennemis!B:B,MATCH(A53,Ennemis!A:A,0)) -> 1 | C53: =(INDEX(Ennemis!G:G,MATCH(A53,Ennemis!A:A,0))+INDEX(Ennemis!H:H,MATCH(A53,Ennemis!A:A,0)))/2 -> 17.5 | D53: =IFERROR(INDEX('Loot Table'!B:B,MATCH(A53,'Loot Table'!A:A,0)),"-") -> Plasma Pistol MK-I | E53: =IFERROR(INDEX('Loot Table'!C:C,MATCH(A53,'Loot Table'!A:A,0)),0) -> 0.15 | F53: =IFERROR(INDEX(Items!D:D,MATCH(D53,Items!A:A,0)),0) -> 100 | G53: {=IFERROR(INDEX('Loot Table'!B:B,MATCH(A53,'Loot Table'!A:A,0)+1),"-")} -> Kevlar Vest | H53: {=IFERROR(INDEX('Loot Table'!C:C,MATCH(A53,'Loot Table'!A:A,0)+1),0)} -> 0.1 | I53: =IFERROR(INDEX(Items!D:D,MATCH(G53,Items!A:A,0)),0) -> 80 | J53: =E53*F53+H53*I53 -> 23 | K53: =C53+J53 -> 40.5 | L53: =IF(C53>0,J53/C53,0) -> 1.3142857
A54: Rogue AI Drone | B54: =INDEX(Ennemis!B:B,MATCH(A54,Ennemis!A:A,0)) -> 2 | C54: =(INDEX(Ennemis!G:G,MATCH(A54,Ennemis!A:A,0))+INDEX(Ennemis!H:H,MATCH(A54,Ennemis!A:A,0)))/2 -> 35 | D54: =IFERROR(INDEX('Loot Table'!B:B,MATCH(A54,'Loot Table'!A:A,0)),"-") -> Neural Disruptor | E54: =IFERROR(INDEX('Loot Table'!C:C,MATCH(A54,'Loot Table'!A:A,0)),0) -> 0.15 | F54: =IFERROR(INDEX(Items!D:D,MATCH(D54,Items!A:A,0)),0) -> 500 | G54: {=IFERROR(INDEX('Loot Table'!B:B,MATCH(A54,'Loot Table'!A:A,0)+1),"-")} -> Neural Accelerator | H54: {=IFERROR(INDEX('Loot Table'!C:C,MATCH(A54,'Loot Table'!A:A,0)+1),0)} -> 0.1 | I54: =IFERROR(INDEX(Items!D:D,MATCH(G54,Items!A:A,0)),0) -> 600 | J54: =E54*F54+H54*I54 -> 135 | K54: =C54+J54 -> 170 | L54: =IF(C54>0,J54/C54,0) -> 3.8571429
A55: Cyber Jackal | B55: =INDEX(Ennemis!B:B,MATCH(A55,Ennemis!A:A,0)) -> 2 | C55: =(INDEX(Ennemis!G:G,MATCH(A55,Ennemis!A:A,0))+INDEX(Ennemis!H:H,MATCH(A55,Ennemis!A:A,0)))/2 -> 27.5 | D55: =IFERROR(INDEX('Loot Table'!B:B,MATCH(A55,'Loot Table'!A:A,0)),"-") -> Nanoweave Jacket | E55: =IFERROR(INDEX('Loot Table'!C:C,MATCH(A55,'Loot Table'!A:A,0)),0) -> 0.15 | F55: =IFERROR(INDEX(Items!D:D,MATCH(D55,Items!A:A,0)),0) -> 400 | G55: {=IFERROR(INDEX('Loot Table'!B:B,MATCH(A55,'Loot Table'!A:A,0)+1),"-")} -> Haptic Amplifier | H55: {=IFERROR(INDEX('Loot Table'!C:C,MATCH(A55,'Loot Table'!A:A,0)+1),0)} -> 0.12 | I55: =IFERROR(INDEX(Items!D:D,MATCH(G55,Items!A:A,0)),0) -> 50000 | J55: =E55*F55+H55*I55 -> 6060 | K55: =C55+J55 -> 6087.5 | L55: =IF(C55>0,J55/C55,0) -> 220.36364
A56: DataWraith | B56: =INDEX(Ennemis!B:B,MATCH(A56,Ennemis!A:A,0)) -> 2 | C56: =(INDEX(Ennemis!G:G,MATCH(A56,Ennemis!A:A,0))+INDEX(Ennemis!H:H,MATCH(A56,Ennemis!A:A,0)))/2 -> 42.5 | D56: =IFERROR(INDEX('Loot Table'!B:B,MATCH(A56,'Loot Table'!A:A,0)),"-") -> Haptic Amplifier | E56: =IFERROR(INDEX('Loot Table'!C:C,MATCH(A56,'Loot Table'!A:A,0)),0) -> 0.12 | F56: =IFERROR(INDEX(Items!D:D,MATCH(D56,Items!A:A,0)),0) -> 50000 | G56: {=IFERROR(INDEX('Loot Table'!B:B,MATCH(A56,'Loot Table'!A:A,0)+1),"-")} -> MedGel Capsule | H56: {=IFERROR(INDEX('Loot Table'!C:C,MATCH(A56,'Loot Table'!A:A,0)+1),0)} -> 0.2 | I56: =IFERROR(INDEX(Items!D:D,MATCH(G56,Items!A:A,0)),0) -> 80 | J56: =E56*F56+H56*I56 -> 6016 | K56: =C56+J56 -> 6058.5 | L56: =IF(C56>0,J56/C56,0) -> 141.55294
A57: Corp Security Bot | B57: =INDEX(Ennemis!B:B,MATCH(A57,Ennemis!A:A,0)) -> 3 | C57: =(INDEX(Ennemis!G:G,MATCH(A57,Ennemis!A:A,0))+INDEX(Ennemis!H:H,MATCH(A57,Ennemis!A:A,0)))/2 -> 85 | D57: =IFERROR(INDEX('Loot Table'!B:B,MATCH(A57,'Loot Table'!A:A,0)),"-") -> Titanium Exosuit | E57: =IFERROR(INDEX('Loot Table'!C:C,MATCH(A57,'Loot Table'!A:A,0)),0) -> 0.12 | F57: =IFERROR(INDEX(Items!D:D,MATCH(D57,Items!A:A,0)),0) -> 1200 | G57: {=IFERROR(INDEX('Loot Table'!B:B,MATCH(A57,'Loot Table'!A:A,0)+1),"-")} -> Railgun X-7 | H57: {=IFERROR(INDEX('Loot Table'!C:C,MATCH(A57,'Loot Table'!A:A,0)+1),0)} -> 0.1 | I57: =IFERROR(INDEX(Items!D:D,MATCH(G57,Items!A:A,0)),0) -> 1500 | J57: =E57*F57+H57*I57 -> 294 | K57: =C57+J57 -> 379 | L57: =IF(C57>0,J57/C57,0) -> 3.4588235
A58: Netrunner Assassin | B58: =INDEX(Ennemis!B:B,MATCH(A58,Ennemis!A:A,0)) -> 3 | C58: =(INDEX(Ennemis!G:G,MATCH(A58,Ennemis!A:A,0))+INDEX(Ennemis!H:H,MATCH(A58,Ennemis!A:A,0)))/2 -> 105 | D58: =IFERROR(INDEX('Loot Table'!B:B,MATCH(A58,'Loot Table'!A:A,0)),"-") -> Railgun X-7 | E58: =IFERROR(INDEX('Loot Table'!C:C,MATCH(A58,'Loot Table'!A:A,0)),0) -> 0.1 | F58: =IFERROR(INDEX(Items!D:D,MATCH(D58,Items!A:A,0)),0) -> 1500 | G58: {=IFERROR(INDEX('Loot Table'!B:B,MATCH(A58,'Loot Table'!A:A,0)+1),"-")} -> Synaptic Overdrive | H58: {=IFERROR(INDEX('Loot Table'!C:C,MATCH(A58,'Loot Table'!A:A,0)+1),0)} -> 0.08 | I58: =IFERROR(INDEX(Items!D:D,MATCH(G58,Items!A:A,0)),0) -> 2000 | J58: =E58*F58+H58*I58 -> 310 | K58: =C58+J58 -> 415 | L58: =IF(C58>0,J58/C58,0) -> 2.952381
A59: Mech Walker | B59: =INDEX(Ennemis!B:B,MATCH(A59,Ennemis!A:A,0)) -> 3 | C59: =(INDEX(Ennemis!G:G,MATCH(A59,Ennemis!A:A,0))+INDEX(Ennemis!H:H,MATCH(A59,Ennemis!A:A,0)))/2 -> 140 | D59: =IFERROR(INDEX('Loot Table'!B:B,MATCH(A59,'Loot Table'!A:A,0)),"-") -> Neural Click Matrix | E59: =IFERROR(INDEX('Loot Table'!C:C,MATCH(A59,'Loot Table'!A:A,0)),0) -> 0.1 | F59: =IFERROR(INDEX(Items!D:D,MATCH(D59,Items!A:A,0)),0) -> 500000 | G59: {=IFERROR(INDEX('Loot Table'!B:B,MATCH(A59,'Loot Table'!A:A,0)+1),"-")} -> Phoenix Serum | H59: {=IFERROR(INDEX('Loot Table'!C:C,MATCH(A59,'Loot Table'!A:A,0)+1),0)} -> 0.15 | I59: =IFERROR(INDEX(Items!D:D,MATCH(G59,Items!A:A,0)),0) -> 300 | J59: =E59*F59+H59*I59 -> 50045 | K59: =C59+J59 -> 50185 | L59: =IF(C59>0,J59/C59,0) -> 357.46429
A60: ARCHON | B60: =INDEX(Ennemis!B:B,MATCH(A60,Ennemis!A:A,0)) -> 4 | C60: =(INDEX(Ennemis!G:G,MATCH(A60,Ennemis!A:A,0))+INDEX(Ennemis!H:H,MATCH(A60,Ennemis!A:A,0)))/2 -> 550 | D60: =IFERROR(INDEX('Loot Table'!B:B,MATCH(A60,'Loot Table'!A:A,0)),"-") -> Void Cannon | E60: =IFERROR(INDEX('Loot Table'!C:C,MATCH(A60,'Loot Table'!A:A,0)),0) -> 0.2 | F60: =IFERROR(INDEX(Items!D:D,MATCH(D60,Items!A:A,0)),0) -> 5000 | G60: {=IFERROR(INDEX('Loot Table'!B:B,MATCH(A60,'Loot Table'!A:A,0)+1),"-")} -> Quantum Consciousness | H60: {=IFERROR(INDEX('Loot Table'!C:C,MATCH(A60,'Loot Table'!A:A,0)+1),0)} -> 0.15 | I60: =IFERROR(INDEX(Items!D:D,MATCH(G60,Items!A:A,0)),0) -> 8000 | J60: =E60*F60+H60*I60 -> 2200 | K60: =C60+J60 -> 2750 | L60: =IF(C60>0,J60/C60,0) -> 4
A61: Chrome Dragon | B61: =INDEX(Ennemis!B:B,MATCH(A61,Ennemis!A:A,0)) -> 4 | C61: =(INDEX(Ennemis!G:G,MATCH(A61,Ennemis!A:A,0))+INDEX(Ennemis!H:H,MATCH(A61,Ennemis!A:A,0)))/2 -> 1000 | D61: =IFERROR(INDEX('Loot Table'!B:B,MATCH(A61,'Loot Table'!A:A,0)),"-") -> Quantum Shield Matrix | E61: =IFERROR(INDEX('Loot Table'!C:C,MATCH(A61,'Loot Table'!A:A,0)),0) -> 0.2 | F61: =IFERROR(INDEX(Items!D:D,MATCH(D61,Items!A:A,0)),0) -> 4000 | G61: {=IFERROR(INDEX('Loot Table'!B:B,MATCH(A61,'Loot Table'!A:A,0)+1),"-")} -> Quantum Tap Interface | H61: {=IFERROR(INDEX('Loot Table'!C:C,MATCH(A61,'Loot Table'!A:A,0)+1),0)} -> 0.15 | I61: =IFERROR(INDEX(Items!D:D,MATCH(G61,Items!A:A,0)),0) -> 5000000 | J61: =E61*F61+H61*I61 -> 750800 | K61: =C61+J61 -> 751800 | L61: =IF(C61>0,J61/C61,0) -> 750.8
A62: The Void King | B62: =INDEX(Ennemis!B:B,MATCH(A62,Ennemis!A:A,0)) -> 4 | C62: =(INDEX(Ennemis!G:G,MATCH(A62,Ennemis!A:A,0))+INDEX(Ennemis!H:H,MATCH(A62,Ennemis!A:A,0)))/2 -> 2000 | D62: =IFERROR(INDEX('Loot Table'!B:B,MATCH(A62,'Loot Table'!A:A,0)),"-") -> OMEGA Protocol | E62: =IFERROR(INDEX('Loot Table'!C:C,MATCH(A62,'Loot Table'!A:A,0)),0) -> 0.1 | F62: =IFERROR(INDEX(Items!D:D,MATCH(D62,Items!A:A,0)),0) -> 20000 | G62: {=IFERROR(INDEX('Loot Table'!B:B,MATCH(A62,'Loot Table'!A:A,0)+1),"-")} -> Ghost Shell | H62: {=IFERROR(INDEX('Loot Table'!C:C,MATCH(A62,'Loot Table'!A:A,0)+1),0)} -> 0.1 | I62: =IFERROR(INDEX(Items!D:D,MATCH(G62,Items!A:A,0)),0) -> 18000 | J62: =E62*F62+H62*I62 -> 3800 | K62: =C62+J62 -> 5800 | L62: =IF(C62>0,J62/C62,0) -> 1.9
A63: Black ICE Hound | B63: =INDEX(Ennemis!B:B,MATCH(A63,Ennemis!A:A,0)) -> 5 | C63: =(INDEX(Ennemis!G:G,MATCH(A63,Ennemis!A:A,0))+INDEX(Ennemis!H:H,MATCH(A63,Ennemis!A:A,0)))/2 -> 5000 | D63: =IFERROR(INDEX('Loot Table'!B:B,MATCH(A63,'Loot Table'!A:A,0)),"-") -> Kiroshi Pulse Sync | E63: =IFERROR(INDEX('Loot Table'!C:C,MATCH(A63,'Loot Table'!A:A,0)),0) -> 0.12 | F63: =IFERROR(INDEX(Items!D:D,MATCH(D63,Items!A:A,0)),0) -> 400 | G63: {=IFERROR(INDEX('Loot Table'!B:B,MATCH(A63,'Loot Table'!A:A,0)+1),"-")} -> Sandevistan Lite | H63: {=IFERROR(INDEX('Loot Table'!C:C,MATCH(A63,'Loot Table'!A:A,0)+1),0)} -> 0.08 | I63: =IFERROR(INDEX(Items!D:D,MATCH(G63,Items!A:A,0)),0) -> 1600 | J63: =E63*F63+H63*I63 -> 176 | K63: =C63+J63 -> 5176 | L63: =IF(C63>0,J63/C63,0) -> 0.0352
... A72: Soulkiller Prime | B72: =INDEX(Ennemis!B:B,MATCH(A72,Ennemis!A:A,0)) -> 7 | C72: =(INDEX(Ennemis!G:G,MATCH(A72,Ennemis!A:A,0))+INDEX(Ennemis!H:H,MATCH(A72,Ennemis!A:A,0)))/2 -> 43500 | D72: =IFERROR(INDEX('Loot Table'!B:B,MATCH(A72,'Loot Table'!A:A,0)),"-") -> Blackwall Breacher | E72: =IFERROR(INDEX('Loot Table'!C:C,MATCH(A72,'Loot Table'!A:A,0)),0) -> 0.12 | F72: =IFERROR(INDEX(Items!D:D,MATCH(D72,Items!A:A,0)),0) -> 240000 | G72: {=IFERROR(INDEX('Loot Table'!B:B,MATCH(A72,'Loot Table'!A:A,0)+1),"-")} -> Mikoshi Nullskin | H72: {=IFERROR(INDEX('Loot Table'!C:C,MATCH(A72,'Loot Table'!A:A,0)+1),0)} -> 0.12 | I72: =IFERROR(INDEX(Items!D:D,MATCH(G72,Items!A:A,0)),0) -> 210000 | J72: =E72*F72+H72*I72 -> 54000 | K72: =C72+J72 -> 97500 | L72: =IF(C72>0,J72/C72,0) -> 1.2413793
A75: 📈 PROGRESSION SCALING — COURBE DE PUISSANCE
A76: Niveau | B76: XP Cumulé | C76: HP Joueur | D76: ATK Joueur | E76: DEF Joueur | F76: Tier Donjon Dispo | G76: HP Ennemi Max Tier | H76: ATK Ennemi Max Tier | I76: DEF Ennemi Max Tier | J76: Surplus HP % | K76: Surplus ATK % | L76: ⚠️ Difficulté
A77: 1 | B77: =INDEX('Progression Niveaux'!C:C,MATCH(A77,'Progression Niveaux'!A:A,0)) -> 0 | C77: =INDEX('Progression Niveaux'!D:D,MATCH(A77,'Progression Niveaux'!A:A,0)) -> 100 | D77: =INDEX('Progression Niveaux'!E:E,MATCH(A77,'Progression Niveaux'!A:A,0)) -> 10 | E77: =INDEX('Progression Niveaux'!F:F,MATCH(A77,'Progression Niveaux'!A:A,0)) -> 5 | F77: 1 | G77: =_xlfn.MAXIFS(Ennemis!C:C,Ennemis!B:B,F77) -> 50 | H77: =_xlfn.MAXIFS(Ennemis!D:D,Ennemis!B:B,F77) -> 8 | I77: =_xlfn.MAXIFS(Ennemis!E:E,Ennemis!B:B,F77) -> 3 | J77: =(C77-G77)/G77 -> 1 | K77: =(D77-H77)/H77 -> 0.25 | L77: =IF(J77<-0.5,"💀 Trop dur",IF(J77<0,"⚠️ Challengeant",IF(J77<1,"✅ Équilibré","😴 Trop facile"))) -> 😴 Trop facile
A78: 3 | B78: =INDEX('Progression Niveaux'!C:C,MATCH(A78,'Progression Niveaux'!A:A,0)) -> 300 | C78: =INDEX('Progression Niveaux'!D:D,MATCH(A78,'Progression Niveaux'!A:A,0)) -> 123 | D78: =INDEX('Progression Niveaux'!E:E,MATCH(A78,'Progression Niveaux'!A:A,0)) -> 14 | E78: =INDEX('Progression Niveaux'!F:F,MATCH(A78,'Progression Niveaux'!A:A,0)) -> 7 | F78: 2 | G78: =_xlfn.MAXIFS(Ennemis!C:C,Ennemis!B:B,F78) -> 80 | H78: =_xlfn.MAXIFS(Ennemis!D:D,Ennemis!B:B,F78) -> 20 | I78: =_xlfn.MAXIFS(Ennemis!E:E,Ennemis!B:B,F78) -> 10 | J78: =(C78-G78)/G78 -> 0.5375 | K78: =(D78-H78)/H78 -> -0.3 | L78: =IF(J78<-0.5,"💀 Trop dur",IF(J78<0,"⚠️ Challengeant",IF(J78<1,"✅ Équilibré","😴 Trop facile"))) -> ✅ Équilibré
A79: 5 | B79: =INDEX('Progression Niveaux'!C:C,MATCH(A79,'Progression Niveaux'!A:A,0)) -> 1000 | C79: =INDEX('Progression Niveaux'!D:D,MATCH(A79,'Progression Niveaux'!A:A,0)) -> 152 | D79: =INDEX('Progression Niveaux'!E:E,MATCH(A79,'Progression Niveaux'!A:A,0)) -> 19 | E79: =INDEX('Progression Niveaux'!F:F,MATCH(A79,'Progression Niveaux'!A:A,0)) -> 10 | F79: 2 | G79: =_xlfn.MAXIFS(Ennemis!C:C,Ennemis!B:B,F79) -> 80 | H79: =_xlfn.MAXIFS(Ennemis!D:D,Ennemis!B:B,F79) -> 20 | I79: =_xlfn.MAXIFS(Ennemis!E:E,Ennemis!B:B,F79) -> 10 | J79: =(C79-G79)/G79 -> 0.9 | K79: =(D79-H79)/H79 -> -0.05 | L79: =IF(J79<-0.5,"💀 Trop dur",IF(J79<0,"⚠️ Challengeant",IF(J79<1,"✅ Équilibré","😴 Trop facile"))) -> ✅ Équilibré
A80: 8 | B80: =INDEX('Progression Niveaux'!C:C,MATCH(A80,'Progression Niveaux'!A:A,0)) -> 2800 | C80: =INDEX('Progression Niveaux'!D:D,MATCH(A80,'Progression Niveaux'!A:A,0)) -> 207 | D80: =INDEX('Progression Niveaux'!E:E,MATCH(A80,'Progression Niveaux'!A:A,0)) -> 28 | E80: =INDEX('Progression Niveaux'!F:F,MATCH(A80,'Progression Niveaux'!A:A,0)) -> 16 | F80: 3 | G80: =_xlfn.MAXIFS(Ennemis!C:C,Ennemis!B:B,F80) -> 200 | H80: =_xlfn.MAXIFS(Ennemis!D:D,Ennemis!B:B,F80) -> 35 | I80: =_xlfn.MAXIFS(Ennemis!E:E,Ennemis!B:B,F80) -> 25 | J80: =(C80-G80)/G80 -> 0.035 | K80: =(D80-H80)/H80 -> -0.2 | L80: =IF(J80<-0.5,"💀 Trop dur",IF(J80<0,"⚠️ Challengeant",IF(J80<1,"✅ Équilibré","😴 Trop facile"))) -> ✅ Équilibré
A81: 10 | B81: =INDEX('Progression Niveaux'!C:C,MATCH(A81,'Progression Niveaux'!A:A,0)) -> 4500 | C81: =INDEX('Progression Niveaux'!D:D,MATCH(A81,'Progression Niveaux'!A:A,0)) -> 251 | D81: =INDEX('Progression Niveaux'!E:E,MATCH(A81,'Progression Niveaux'!A:A,0)) -> 35 | E81: =INDEX('Progression Niveaux'!F:F,MATCH(A81,'Progression Niveaux'!A:A,0)) -> 21 | F81: 3 | G81: =_xlfn.MAXIFS(Ennemis!C:C,Ennemis!B:B,F81) -> 200 | H81: =_xlfn.MAXIFS(Ennemis!D:D,Ennemis!B:B,F81) -> 35 | I81: =_xlfn.MAXIFS(Ennemis!E:E,Ennemis!B:B,F81) -> 25 | J81: =(C81-G81)/G81 -> 0.255 | K81: =(D81-H81)/H81 -> 0 | L81: =IF(J81<-0.5,"💀 Trop dur",IF(J81<0,"⚠️ Challengeant",IF(J81<1,"✅ Équilibré","😴 Trop facile"))) -> ✅ Équilibré
A82: 15 | B82: =INDEX('Progression Niveaux'!C:C,MATCH(A82,'Progression Niveaux'!A:A,0)) -> 10500 | C82: =INDEX('Progression Niveaux'!D:D,MATCH(A82,'Progression Niveaux'!A:A,0)) -> 387 | D82: =INDEX('Progression Niveaux'!E:E,MATCH(A82,'Progression Niveaux'!A:A,0)) -> 56 | E82: =INDEX('Progression Niveaux'!F:F,MATCH(A82,'Progression Niveaux'!A:A,0)) -> 37 | F82: 4 | G82: =_xlfn.MAXIFS(Ennemis!C:C,Ennemis!B:B,F82) -> 1200 | H82: =_xlfn.MAXIFS(Ennemis!D:D,Ennemis!B:B,F82) -> 80 | I82: =_xlfn.MAXIFS(Ennemis!E:E,Ennemis!B:B,F82) -> 50 | J82: =(C82-G82)/G82 -> -0.6775 | K82: =(D82-H82)/H82 -> -0.3 | L82: =IF(J82<-0.5,"💀 Trop dur",IF(J82<0,"⚠️ Challengeant",IF(J82<1,"✅ Équilibré","😴 Trop facile"))) -> 💀 Trop dur
A83: 20 | B83: =INDEX('Progression Niveaux'!C:C,MATCH(A83,'Progression Niveaux'!A:A,0)) -> 19000 | C83: =INDEX('Progression Niveaux'!D:D,MATCH(A83,'Progression Niveaux'!A:A,0)) -> 561 | D83: =INDEX('Progression Niveaux'!E:E,MATCH(A83,'Progression Niveaux'!A:A,0)) -> 82 | E83: =INDEX('Progression Niveaux'!F:F,MATCH(A83,'Progression Niveaux'!A:A,0)) -> 58 | F83: 5 | G83: =_xlfn.MAXIFS(Ennemis!C:C,Ennemis!B:B,F83) -> 2600 | H83: =_xlfn.MAXIFS(Ennemis!D:D,Ennemis!B:B,F83) -> 135 | I83: =_xlfn.MAXIFS(Ennemis!E:E,Ennemis!B:B,F83) -> 95 | J83: =(C83-G83)/G83 -> -0.78423077 | K83: =(D83-H83)/H83 -> -0.39259259 | L83: =IF(J83<-0.5,"💀 Trop dur",IF(J83<0,"⚠️ Challengeant",IF(J83<1,"✅ Équilibré","😴 Trop facile"))) -> 💀 Trop dur
A84: 24 | B84: =INDEX('Progression Niveaux'!C:C,MATCH(A84,'Progression Niveaux'!A:A,0)) -> 27600 | C84: =INDEX('Progression Niveaux'!D:D,MATCH(A84,'Progression Niveaux'!A:A,0)) -> 727 | D84: =INDEX('Progression Niveaux'!E:E,MATCH(A84,'Progression Niveaux'!A:A,0)) -> 106 | E84: =INDEX('Progression Niveaux'!F:F,MATCH(A84,'Progression Niveaux'!A:A,0)) -> 78 | F84: 5 | G84: =_xlfn.MAXIFS(Ennemis!C:C,Ennemis!B:B,F84) -> 2600 | H84: =_xlfn.MAXIFS(Ennemis!D:D,Ennemis!B:B,F84) -> 135 | I84: =_xlfn.MAXIFS(Ennemis!E:E,Ennemis!B:B,F84) -> 95 | J84: =(C84-G84)/G84 -> -0.72038462 | K84: =(D84-H84)/H84 -> -0.21481481 | L84: =IF(J84<-0.5,"💀 Trop dur",IF(J84<0,"⚠️ Challengeant",IF(J84<1,"✅ Équilibré","😴 Trop facile"))) -> 💀 Trop dur
A85: 29 | B85: =INDEX('Progression Niveaux'!C:C,MATCH(A85,'Progression Niveaux'!A:A,0)) -> 40600 | C85: =INDEX('Progression Niveaux'!D:D,MATCH(A85,'Progression Niveaux'!A:A,0)) -> 968 | D85: =INDEX('Progression Niveaux'!E:E,MATCH(A85,'Progression Niveaux'!A:A,0)) -> 141 | E85: =INDEX('Progression Niveaux'!F:F,MATCH(A85,'Progression Niveaux'!A:A,0)) -> 108 | F85: 6 | G85: =_xlfn.MAXIFS(Ennemis!C:C,Ennemis!B:B,F85) -> 4700 | H85: =_xlfn.MAXIFS(Ennemis!D:D,Ennemis!B:B,F85) -> 195 | I85: =_xlfn.MAXIFS(Ennemis!E:E,Ennemis!B:B,F85) -> 135 | J85: =(C85-G85)/G85 -> -0.79404255 | K85: =(D85-H85)/H85 -> -0.27692308 | L85: =IF(J85<-0.5,"💀 Trop dur",IF(J85<0,"⚠️ Challengeant",IF(J85<1,"✅ Équilibré","😴 Trop facile"))) -> 💀 Trop dur
A86: 34 | B86: =INDEX('Progression Niveaux'!C:C,MATCH(A86,'Progression Niveaux'!A:A,0)) -> 56100 | C86: =INDEX('Progression Niveaux'!D:D,MATCH(A86,'Progression Niveaux'!A:A,0)) -> 1247 | D86: =INDEX('Progression Niveaux'!E:E,MATCH(A86,'Progression Niveaux'!A:A,0)) -> 181 | E86: =INDEX('Progression Niveaux'!F:F,MATCH(A86,'Progression Niveaux'!A:A,0)) -> 143 | F86: 6 | G86: =_xlfn.MAXIFS(Ennemis!C:C,Ennemis!B:B,F86) -> 4700 | H86: =_xlfn.MAXIFS(Ennemis!D:D,Ennemis!B:B,F86) -> 195 | I86: =_xlfn.MAXIFS(Ennemis!E:E,Ennemis!B:B,F86) -> 135 | J86: =(C86-G86)/G86 -> -0.73468085 | K86: =(D86-H86)/H86 -> -0.071794872 | L86: =IF(J86<-0.5,"💀 Trop dur",IF(J86<0,"⚠️ Challengeant",IF(J86<1,"✅ Équilibré","😴 Trop facile"))) -> 💀 Trop dur
A87: 40 | B87: =INDEX('Progression Niveaux'!C:C,MATCH(A87,'Progression Niveaux'!A:A,0)) -> 78000 | C87: =INDEX('Progression Niveaux'!D:D,MATCH(A87,'Progression Niveaux'!A:A,0)) -> 1631 | D87: =INDEX('Progression Niveaux'!E:E,MATCH(A87,'Progression Niveaux'!A:A,0)) -> 236 | E87: =INDEX('Progression Niveaux'!F:F,MATCH(A87,'Progression Niveaux'!A:A,0)) -> 192 | F87: 7 | G87: =_xlfn.MAXIFS(Ennemis!C:C,Ennemis!B:B,F87) -> 9800 | H87: =_xlfn.MAXIFS(Ennemis!D:D,Ennemis!B:B,F87) -> 285 | I87: =_xlfn.MAXIFS(Ennemis!E:E,Ennemis!B:B,F87) -> 220 | J87: =(C87-G87)/G87 -> -0.83357143 | K87: =(D87-H87)/H87 -> -0.17192982 | L87: =IF(J87<-0.5,"💀 Trop dur",IF(J87<0,"⚠️ Challengeant",IF(J87<1,"✅ Équilibré","😴 Trop facile"))) -> 💀 Trop dur
A88: 48 | B88: =INDEX('Progression Niveaux'!C:C,MATCH(A88,'Progression Niveaux'!A:A,0)) -> 112800 | C88: =INDEX('Progression Niveaux'!D:D,MATCH(A88,'Progression Niveaux'!A:A,0)) -> 2227 | D88: =INDEX('Progression Niveaux'!E:E,MATCH(A88,'Progression Niveaux'!A:A,0)) -> 320 | E88: =INDEX('Progression Niveaux'!F:F,MATCH(A88,'Progression Niveaux'!A:A,0)) -> 268 | F88: 7 | G88: =_xlfn.MAXIFS(Ennemis!C:C,Ennemis!B:B,F88) -> 9800 | H88: =_xlfn.MAXIFS(Ennemis!D:D,Ennemis!B:B,F88) -> 285 | I88: =_xlfn.MAXIFS(Ennemis!E:E,Ennemis!B:B,F88) -> 220 | J88: =(C88-G88)/G88 -> -0.7727551 | K88: =(D88-H88)/H88 -> 0.12280702 | L88: =IF(J88<-0.5,"💀 Trop dur",IF(J88<0,"⚠️ Challengeant",IF(J88<1,"✅ Équilibré","😴 Trop facile"))) -> 💀 Trop dur
... A93: 150 | B93: =INDEX('Progression Niveaux'!C:C,MATCH(A93,'Progression Niveaux'!A:A,0)) -> 1117500 | C93: =INDEX('Progression Niveaux'!D:D,MATCH(A93,'Progression Niveaux'!A:A,0)) -> 18241 | D93: =INDEX('Progression Niveaux'!E:E,MATCH(A93,'Progression Niveaux'!A:A,0)) -> 2513 | E93: =INDEX('Progression Niveaux'!F:F,MATCH(A93,'Progression Niveaux'!A:A,0)) -> 2359 | F93: 7 | G93: =_xlfn.MAXIFS(Ennemis!C:C,Ennemis!B:B,F93) -> 9800 | H93: =_xlfn.MAXIFS(Ennemis!D:D,Ennemis!B:B,F93) -> 285 | I93: =_xlfn.MAXIFS(Ennemis!E:E,Ennemis!B:B,F93) -> 220 | J93: =(C93-G93)/G93 -> 0.86132653 | K93: =(D93-H93)/H93 -> 7.8175439 | L93: =IF(J93<-0.5,"💀 Trop dur",IF(J93<0,"⚠️ Challengeant",IF(J93<1,"✅ Équilibré","😴 Trop facile"))) -> ✅ Équilibré
A96: 🏰 DONJON — DIFFICULTÉ PAR ÉTAGE
A97: Étage | B97: Nom | C97: Niv. Min | D97: Joueurs Min | E97: Joueurs Max | F97: HP Joueur @Min | G97: ATK Joueur @Min | H97: Boss? | I97: HP Boss | J97: ATK Boss | K97: Coups Solo vs Boss | L97: ⚠️ Solo Possible?
A98: 1 | B98: =INDEX(Donjon!B:B,MATCH(A98,Donjon!A:A,0)) -> Neon Alley | C98: =INDEX(Donjon!C:C,MATCH(A98,Donjon!A:A,0)) -> 1 | D98: =INDEX(Donjon!F:F,MATCH(A98,Donjon!A:A,0)) -> 1 | E98: =INDEX(Donjon!G:G,MATCH(A98,Donjon!A:A,0)) -> 4 | F98: =INDEX('Progression Niveaux'!D:D,MATCH(C98,'Progression Niveaux'!A:A,0)) -> 100 | G98: =INDEX('Progression Niveaux'!E:E,MATCH(C98,'Progression Niveaux'!A:A,0)) -> 10 | H98: =IF(INDEX(Donjon!E:E,MATCH(A98,Donjon!A:A,0))="","-",INDEX(Donjon!E:E,MATCH(A98,Donjon!A:A,0))) -> - | I98: =IFERROR(INDEX(Ennemis!C:C,MATCH(H98,Ennemis!A:A,0)),0) -> 0 | J98: =IFERROR(INDEX(Ennemis!D:D,MATCH(H98,Ennemis!A:A,0)),0) -> 0 | K98: =IF(I98>0,ROUNDUP(I98/MAX(G98-IFERROR(INDEX(Ennemis!E:E,MATCH(H98,Ennemis!A:A,0)),0),1),0),"-") -> - | L98: =IF(I98=0,"-",IF(AND(D98=1,K98<50),"✅ Oui",IF(D98>1,"🚫 Groupe requis","⚠️ Très long"))) -> -
A99: 2 | B99: =INDEX(Donjon!B:B,MATCH(A99,Donjon!A:A,0)) -> Abandoned Metro | C99: =INDEX(Donjon!C:C,MATCH(A99,Donjon!A:A,0)) -> 3 | D99: =INDEX(Donjon!F:F,MATCH(A99,Donjon!A:A,0)) -> 1 | E99: =INDEX(Donjon!G:G,MATCH(A99,Donjon!A:A,0)) -> 4 | F99: =INDEX('Progression Niveaux'!D:D,MATCH(C99,'Progression Niveaux'!A:A,0)) -> 123 | G99: =INDEX('Progression Niveaux'!E:E,MATCH(C99,'Progression Niveaux'!A:A,0)) -> 14 | H99: =IF(INDEX(Donjon!E:E,MATCH(A99,Donjon!A:A,0))="","-",INDEX(Donjon!E:E,MATCH(A99,Donjon!A:A,0))) -> - | I99: =IFERROR(INDEX(Ennemis!C:C,MATCH(H99,Ennemis!A:A,0)),0) -> 0 | J99: =IFERROR(INDEX(Ennemis!D:D,MATCH(H99,Ennemis!A:A,0)),0) -> 0 | K99: =IF(I99>0,ROUNDUP(I99/MAX(G99-IFERROR(INDEX(Ennemis!E:E,MATCH(H99,Ennemis!A:A,0)),0),1),0),"-") -> - | L99: =IF(I99=0,"-",IF(AND(D99=1,K99<50),"✅ Oui",IF(D99>1,"🚫 Groupe requis","⚠️ Très long"))) -> -
A100: 3 | B100: =INDEX(Donjon!B:B,MATCH(A100,Donjon!A:A,0)) -> Data Catacombs | C100: =INDEX(Donjon!C:C,MATCH(A100,Donjon!A:A,0)) -> 5 | D100: =INDEX(Donjon!F:F,MATCH(A100,Donjon!A:A,0)) -> 1 | E100: =INDEX(Donjon!G:G,MATCH(A100,Donjon!A:A,0)) -> 4 | F100: =INDEX('Progression Niveaux'!D:D,MATCH(C100,'Progression Niveaux'!A:A,0)) -> 152 | G100: =INDEX('Progression Niveaux'!E:E,MATCH(C100,'Progression Niveaux'!A:A,0)) -> 19 | H100: =IF(INDEX(Donjon!E:E,MATCH(A100,Donjon!A:A,0))="","-",INDEX(Donjon!E:E,MATCH(A100,Donjon!A:A,0))) -> ARCHON | I100: =IFERROR(INDEX(Ennemis!C:C,MATCH(H100,Ennemis!A:A,0)),0) -> 500 | J100: =IFERROR(INDEX(Ennemis!D:D,MATCH(H100,Ennemis!A:A,0)),0) -> 50 | K100: =IF(I100>0,ROUNDUP(I100/MAX(G100-IFERROR(INDEX(Ennemis!E:E,MATCH(H100,Ennemis!A:A,0)),0),1),0),"-") -> 500 | L100: =IF(I100=0,"-",IF(AND(D100=1,K100<50),"✅ Oui",IF(D100>1,"🚫 Groupe requis","⚠️ Très long"))) -> ⚠️ Très long
A101: 4 | B101: =INDEX(Donjon!B:B,MATCH(A101,Donjon!A:A,0)) -> Corporate Spire - Lower | C101: =INDEX(Donjon!C:C,MATCH(A101,Donjon!A:A,0)) -> 8 | D101: =INDEX(Donjon!F:F,MATCH(A101,Donjon!A:A,0)) -> 2 | E101: =INDEX(Donjon!G:G,MATCH(A101,Donjon!A:A,0)) -> 4 | F101: =INDEX('Progression Niveaux'!D:D,MATCH(C101,'Progression Niveaux'!A:A,0)) -> 207 | G101: =INDEX('Progression Niveaux'!E:E,MATCH(C101,'Progression Niveaux'!A:A,0)) -> 28 | H101: =IF(INDEX(Donjon!E:E,MATCH(A101,Donjon!A:A,0))="","-",INDEX(Donjon!E:E,MATCH(A101,Donjon!A:A,0))) -> - | I101: =IFERROR(INDEX(Ennemis!C:C,MATCH(H101,Ennemis!A:A,0)),0) -> 0 | J101: =IFERROR(INDEX(Ennemis!D:D,MATCH(H101,Ennemis!A:A,0)),0) -> 0 | K101: =IF(I101>0,ROUNDUP(I101/MAX(G101-IFERROR(INDEX(Ennemis!E:E,MATCH(H101,Ennemis!A:A,0)),0),1),0),"-") -> - | L101: =IF(I101=0,"-",IF(AND(D101=1,K101<50),"✅ Oui",IF(D101>1,"🚫 Groupe requis","⚠️ Très long"))) -> -
A102: 5 | B102: =INDEX(Donjon!B:B,MATCH(A102,Donjon!A:A,0)) -> Corporate Spire - Upper | C102: =INDEX(Donjon!C:C,MATCH(A102,Donjon!A:A,0)) -> 10 | D102: =INDEX(Donjon!F:F,MATCH(A102,Donjon!A:A,0)) -> 2 | E102: =INDEX(Donjon!G:G,MATCH(A102,Donjon!A:A,0)) -> 4 | F102: =INDEX('Progression Niveaux'!D:D,MATCH(C102,'Progression Niveaux'!A:A,0)) -> 251 | G102: =INDEX('Progression Niveaux'!E:E,MATCH(C102,'Progression Niveaux'!A:A,0)) -> 35 | H102: =IF(INDEX(Donjon!E:E,MATCH(A102,Donjon!A:A,0))="","-",INDEX(Donjon!E:E,MATCH(A102,Donjon!A:A,0))) -> Chrome Dragon | I102: =IFERROR(INDEX(Ennemis!C:C,MATCH(H102,Ennemis!A:A,0)),0) -> 800 | J102: =IFERROR(INDEX(Ennemis!D:D,MATCH(H102,Ennemis!A:A,0)),0) -> 60 | K102: =IF(I102>0,ROUNDUP(I102/MAX(G102-IFERROR(INDEX(Ennemis!E:E,MATCH(H102,Ennemis!A:A,0)),0),1),0),"-") -> 800 | L102: =IF(I102=0,"-",IF(AND(D102=1,K102<50),"✅ Oui",IF(D102>1,"🚫 Groupe requis","⚠️ Très long"))) -> 🚫 Groupe requis
A103: 6 | B103: =INDEX(Donjon!B:B,MATCH(A103,Donjon!A:A,0)) -> The Void | C103: =INDEX(Donjon!C:C,MATCH(A103,Donjon!A:A,0)) -> 15 | D103: =INDEX(Donjon!F:F,MATCH(A103,Donjon!A:A,0)) -> 3 | E103: =INDEX(Donjon!G:G,MATCH(A103,Donjon!A:A,0)) -> 4 | F103: =INDEX('Progression Niveaux'!D:D,MATCH(C103,'Progression Niveaux'!A:A,0)) -> 387 | G103: =INDEX('Progression Niveaux'!E:E,MATCH(C103,'Progression Niveaux'!A:A,0)) -> 56 | H103: =IF(INDEX(Donjon!E:E,MATCH(A103,Donjon!A:A,0))="","-",INDEX(Donjon!E:E,MATCH(A103,Donjon!A:A,0))) -> The Void King | I103: =IFERROR(INDEX(Ennemis!C:C,MATCH(H103,Ennemis!A:A,0)),0) -> 1200 | J103: =IFERROR(INDEX(Ennemis!D:D,MATCH(H103,Ennemis!A:A,0)),0) -> 80 | K103: =IF(I103>0,ROUNDUP(I103/MAX(G103-IFERROR(INDEX(Ennemis!E:E,MATCH(H103,Ennemis!A:A,0)),0),1),0),"-") -> 200 | L103: =IF(I103=0,"-",IF(AND(D103=1,K103<50),"✅ Oui",IF(D103>1,"🚫 Groupe requis","⚠️ Très long"))) -> 🚫 Groupe requis
A104: 7 | B104: =INDEX(Donjon!B:B,MATCH(A104,Donjon!A:A,0)) -> Pacifica Black Site | C104: =INDEX(Donjon!C:C,MATCH(A104,Donjon!A:A,0)) -> 20 | D104: =INDEX(Donjon!F:F,MATCH(A104,Donjon!A:A,0)) -> 2 | E104: =INDEX(Donjon!G:G,MATCH(A104,Donjon!A:A,0)) -> 4 | F104: =INDEX('Progression Niveaux'!D:D,MATCH(C104,'Progression Niveaux'!A:A,0)) -> 561 | G104: =INDEX('Progression Niveaux'!E:E,MATCH(C104,'Progression Niveaux'!A:A,0)) -> 82 | H104: =IF(INDEX(Donjon!E:E,MATCH(A104,Donjon!A:A,0))="","-",INDEX(Donjon!E:E,MATCH(A104,Donjon!A:A,0))) -> - | I104: =IFERROR(INDEX(Ennemis!C:C,MATCH(H104,Ennemis!A:A,0)),0) -> 0 | J104: =IFERROR(INDEX(Ennemis!D:D,MATCH(H104,Ennemis!A:A,0)),0) -> 0 | K104: =IF(I104>0,ROUNDUP(I104/MAX(G104-IFERROR(INDEX(Ennemis!E:E,MATCH(H104,Ennemis!A:A,0)),0),1),0),"-") -> - | L104: =IF(I104=0,"-",IF(AND(D104=1,K104<50),"✅ Oui",IF(D104>1,"🚫 Groupe requis","⚠️ Très long"))) -> -
A105: 8 | B105: =INDEX(Donjon!B:B,MATCH(A105,Donjon!A:A,0)) -> Dogtown Kill Corridors | C105: =INDEX(Donjon!C:C,MATCH(A105,Donjon!A:A,0)) -> 24 | D105: =INDEX(Donjon!F:F,MATCH(A105,Donjon!A:A,0)) -> 2 | E105: =INDEX(Donjon!G:G,MATCH(A105,Donjon!A:A,0)) -> 4 | F105: =INDEX('Progression Niveaux'!D:D,MATCH(C105,'Progression Niveaux'!A:A,0)) -> 727 | G105: =INDEX('Progression Niveaux'!E:E,MATCH(C105,'Progression Niveaux'!A:A,0)) -> 106 | H105: =IF(INDEX(Donjon!E:E,MATCH(A105,Donjon!A:A,0))="","-",INDEX(Donjon!E:E,MATCH(A105,Donjon!A:A,0))) -> Cyberpsycho Dragoon | I105: =IFERROR(INDEX(Ennemis!C:C,MATCH(H105,Ennemis!A:A,0)),0) -> 3900 | J105: =IFERROR(INDEX(Ennemis!D:D,MATCH(H105,Ennemis!A:A,0)),0) -> 175 | K105: =IF(I105>0,ROUNDUP(I105/MAX(G105-IFERROR(INDEX(Ennemis!E:E,MATCH(H105,Ennemis!A:A,0)),0),1),0),"-") -> 3900 | L105: =IF(I105=0,"-",IF(AND(D105=1,K105<50),"✅ Oui",IF(D105>1,"🚫 Groupe requis","⚠️ Très long"))) -> 🚫 Groupe requis
A106: 9 | B106: =INDEX(Donjon!B:B,MATCH(A106,Donjon!A:A,0)) -> Arasaka Counterintel Vault | C106: =INDEX(Donjon!C:C,MATCH(A106,Donjon!A:A,0)) -> 29 | D106: =INDEX(Donjon!F:F,MATCH(A106,Donjon!A:A,0)) -> 2 | E106: =INDEX(Donjon!G:G,MATCH(A106,Donjon!A:A,0)) -> 4 | F106: =INDEX('Progression Niveaux'!D:D,MATCH(C106,'Progression Niveaux'!A:A,0)) -> 968 | G106: =INDEX('Progression Niveaux'!E:E,MATCH(C106,'Progression Niveaux'!A:A,0)) -> 141 | H106: =IF(INDEX(Donjon!E:E,MATCH(A106,Donjon!A:A,0))="","-",INDEX(Donjon!E:E,MATCH(A106,Donjon!A:A,0))) -> - | I106: =IFERROR(INDEX(Ennemis!C:C,MATCH(H106,Ennemis!A:A,0)),0) -> 0 | J106: =IFERROR(INDEX(Ennemis!D:D,MATCH(H106,Ennemis!A:A,0)),0) -> 0 | K106: =IF(I106>0,ROUNDUP(I106/MAX(G106-IFERROR(INDEX(Ennemis!E:E,MATCH(H106,Ennemis!A:A,0)),0),1),0),"-") -> - | L106: =IF(I106=0,"-",IF(AND(D106=1,K106<50),"✅ Oui",IF(D106>1,"🚫 Groupe requis","⚠️ Très long"))) -> -
A107: 10 | B107: =INDEX(Donjon!B:B,MATCH(A107,Donjon!A:A,0)) -> Cynosure Relay | C107: =INDEX(Donjon!C:C,MATCH(A107,Donjon!A:A,0)) -> 34 | D107: =INDEX(Donjon!F:F,MATCH(A107,Donjon!A:A,0)) -> 3 | E107: =INDEX(Donjon!G:G,MATCH(A107,Donjon!A:A,0)) -> 4 | F107: =INDEX('Progression Niveaux'!D:D,MATCH(C107,'Progression Niveaux'!A:A,0)) -> 1247 | G107: =INDEX('Progression Niveaux'!E:E,MATCH(C107,'Progression Niveaux'!A:A,0)) -> 181 | H107: =IF(INDEX(Donjon!E:E,MATCH(A107,Donjon!A:A,0))="","-",INDEX(Donjon!E:E,MATCH(A107,Donjon!A:A,0))) -> Blackwall Seraph | I107: =IFERROR(INDEX(Ennemis!C:C,MATCH(H107,Ennemis!A:A,0)),0) -> 6200 | J107: =IFERROR(INDEX(Ennemis!D:D,MATCH(H107,Ennemis!A:A,0)),0) -> 230 | K107: =IF(I107>0,ROUNDUP(I107/MAX(G107-IFERROR(INDEX(Ennemis!E:E,MATCH(H107,Ennemis!A:A,0)),0),1),0),"-") -> 388 | L107: =IF(I107=0,"-",IF(AND(D107=1,K107<50),"✅ Oui",IF(D107>1,"🚫 Groupe requis","⚠️ Très long"))) -> 🚫 Groupe requis
A108: 11 | B108: =INDEX(Donjon!B:B,MATCH(A108,Donjon!A:A,0)) -> Mikoshi Access Spine | C108: =INDEX(Donjon!C:C,MATCH(A108,Donjon!A:A,0)) -> 40 | D108: =INDEX(Donjon!F:F,MATCH(A108,Donjon!A:A,0)) -> 3 | E108: =INDEX(Donjon!G:G,MATCH(A108,Donjon!A:A,0)) -> 4 | F108: =INDEX('Progression Niveaux'!D:D,MATCH(C108,'Progression Niveaux'!A:A,0)) -> 1631 | G108: =INDEX('Progression Niveaux'!E:E,MATCH(C108,'Progression Niveaux'!A:A,0)) -> 236 | H108: =IF(INDEX(Donjon!E:E,MATCH(A108,Donjon!A:A,0))="","-",INDEX(Donjon!E:E,MATCH(A108,Donjon!A:A,0))) -> - | I108: =IFERROR(INDEX(Ennemis!C:C,MATCH(H108,Ennemis!A:A,0)),0) -> 0 | J108: =IFERROR(INDEX(Ennemis!D:D,MATCH(H108,Ennemis!A:A,0)),0) -> 0 | K108: =IF(I108>0,ROUNDUP(I108/MAX(G108-IFERROR(INDEX(Ennemis!E:E,MATCH(H108,Ennemis!A:A,0)),0),1),0),"-") -> - | L108: =IF(I108=0,"-",IF(AND(D108=1,K108<50),"✅ Oui",IF(D108>1,"🚫 Groupe requis","⚠️ Très long"))) -> -
A109: 12 | B109: =INDEX(Donjon!B:B,MATCH(A109,Donjon!A:A,0)) -> Blackwall Breach | C109: =INDEX(Donjon!C:C,MATCH(A109,Donjon!A:A,0)) -> 48 | D109: =INDEX(Donjon!F:F,MATCH(A109,Donjon!A:A,0)) -> 4 | E109: =INDEX(Donjon!G:G,MATCH(A109,Donjon!A:A,0)) -> 4 | F109: =INDEX('Progression Niveaux'!D:D,MATCH(C109,'Progression Niveaux'!A:A,0)) -> 2227 | G109: =INDEX('Progression Niveaux'!E:E,MATCH(C109,'Progression Niveaux'!A:A,0)) -> 320 | H109: =IF(INDEX(Donjon!E:E,MATCH(A109,Donjon!A:A,0))="","-",INDEX(Donjon!E:E,MATCH(A109,Donjon!A:A,0))) -> Soulkiller Prime | I109: =IFERROR(INDEX(Ennemis!C:C,MATCH(H109,Ennemis!A:A,0)),0) -> 9800 | J109: =IFERROR(INDEX(Ennemis!D:D,MATCH(H109,Ennemis!A:A,0)),0) -> 285 | K109: =IF(I109>0,ROUNDUP(I109/MAX(G109-IFERROR(INDEX(Ennemis!E:E,MATCH(H109,Ennemis!A:A,0)),0),1),0),"-") -> 98 | L109: =IF(I109=0,"-",IF(AND(D109=1,K109<50),"✅ Oui",IF(D109>1,"🚫 Groupe requis","⚠️ Très long"))) -> 🚫 Groupe requis
A112: 🐾 COMPANIONS — RAPPORT QUALITÉ/PRIX
A113: Nom | B113: Rareté | C113: Type Bonus | D113: Valeur Bonus | E113: Prix | F113: Valeur/1000 Crédits | G113: ⚠️ Rapport
A114: =Companions!A2 -> Micro-Drone MK1 | B114: =Companions!B2 -> common | C114: =Companions!C2 -> cpc_flat | D114: =Companions!D2 -> 2 | E114: =Companions!E2 -> 500 | F114: =ROUND(D114/(E114/1000),2) -> 4 | G114: =IF(F114>=AVERAGE($F$114:$F$126)*1.2,"🟢 Bon deal",IF(F114<=AVERAGE($F$114:$F$126)*0.8,"🔴 Cher","🟡 Normal")) -> 🟢 Bon deal
A115: =Companions!A3 -> Rat Cybernétique | B115: =Companions!B3 -> common | C115: =Companions!C3 -> cps_flat | D115: =Companions!D3 -> 1 | E115: =Companions!E3 -> 800 | F115: =ROUND(D115/(E115/1000),2) -> 1.25 | G115: =IF(F115>=AVERAGE($F$114:$F$126)*1.2,"🟢 Bon deal",IF(F115<=AVERAGE($F$114:$F$126)*0.8,"🔴 Cher","🟡 Normal")) -> 🔴 Cher
A116: =Companions!A4 -> Bot Bouclier | B116: =Companions!B4 -> common | C116: =Companions!C4 -> def_flat | D116: =Companions!D4 -> 3 | E116: =Companions!E4 -> 600 | F116: =ROUND(D116/(E116/1000),2) -> 5 | G116: =IF(F116>=AVERAGE($F$114:$F$126)*1.2,"🟢 Bon deal",IF(F116<=AVERAGE($F$114:$F$126)*0.8,"🔴 Cher","🟡 Normal")) -> 🟢 Bon deal
A117: =Companions!A5 -> Falcon Electrique | B117: =Companions!B5 -> uncommon | C117: =Companions!C5 -> crit_chance | D117: =Companions!D5 -> 3 | E117: =Companions!E5 -> 2500 | F117: =ROUND(D117/(E117/1000),2) -> 1.2 | G117: =IF(F117>=AVERAGE($F$114:$F$126)*1.2,"🟢 Bon deal",IF(F117<=AVERAGE($F$114:$F$126)*0.8,"🔴 Cher","🟡 Normal")) -> 🔴 Cher
A118: =Companions!A6 -> Spider-Bot | B118: =Companions!B6 -> uncommon | C118: =Companions!C6 -> atk_flat | D118: =Companions!D6 -> 5 | E118: =Companions!E6 -> 3000 | F118: =ROUND(D118/(E118/1000),2) -> 1.67 | G118: =IF(F118>=AVERAGE($F$114:$F$126)*1.2,"🟢 Bon deal",IF(F118<=AVERAGE($F$114:$F$126)*0.8,"🔴 Cher","🟡 Normal")) -> 🟡 Normal
A119: =Companions!A7 -> Nanites Collecteurs | B119: =Companions!B7 -> uncommon | C119: =Companions!C7 -> cps_flat | D119: =Companions!D7 -> 3 | E119: =Companions!E7 -> 3500 | F119: =ROUND(D119/(E119/1000),2) -> 0.86 | G119: =IF(F119>=AVERAGE($F$114:$F$126)*1.2,"🟢 Bon deal",IF(F119<=AVERAGE($F$114:$F$126)*0.8,"🔴 Cher","🟡 Normal")) -> 🔴 Cher
A120: =Companions!A8 -> Drone Tactique V2 | B120: =Companions!B8 -> rare | C120: =Companions!C8 -> cpc_flat | D120: =Companions!D8 -> 8 | E120: =Companions!E8 -> 10000 | F120: =ROUND(D120/(E120/1000),2) -> 0.8 | G120: =IF(F120>=AVERAGE($F$114:$F$126)*1.2,"🟢 Bon deal",IF(F120<=AVERAGE($F$114:$F$126)*0.8,"🔴 Cher","🟡 Normal")) -> 🔴 Cher
A121: =Companions!A9 -> Loup Chrome | B121: =Companions!B9 -> rare | C121: =Companions!C9 -> atk_flat | D121: =Companions!D9 -> 10 | E121: =Companions!E9 -> 12000 | F121: =ROUND(D121/(E121/1000),2) -> 0.83 | G121: =IF(F121>=AVERAGE($F$114:$F$126)*1.2,"🟢 Bon deal",IF(F121<=AVERAGE($F$114:$F$126)*0.8,"🔴 Cher","🟡 Normal")) -> 🔴 Cher
A122: =Companions!A10 -> Medic-Bot | B122: =Companions!B10 -> rare | C122: =Companions!C10 -> hp_flat | D122: =Companions!D10 -> 50 | E122: =Companions!E10 -> 8000 | F122: =ROUND(D122/(E122/1000),2) -> 6.25 | G122: =IF(F122>=AVERAGE($F$114:$F$126)*1.2,"🟢 Bon deal",IF(F122<=AVERAGE($F$114:$F$126)*0.8,"🔴 Cher","🟡 Normal")) -> 🟢 Bon deal
A123: =Companions!A11 -> Phoenix Digital | B123: =Companions!B11 -> epic | C123: =Companions!C11 -> crit_chance | D123: =Companions!D11 -> 8 | E123: =Companions!E11 -> 35000 | F123: =ROUND(D123/(E123/1000),2) -> 0.23 | G123: =IF(F123>=AVERAGE($F$114:$F$126)*1.2,"🟢 Bon deal",IF(F123<=AVERAGE($F$114:$F$126)*0.8,"🔴 Cher","🟡 Normal")) -> 🔴 Cher
A124: =Companions!A12 -> Golem de Données | B124: =Companions!B12 -> epic | C124: =Companions!C12 -> def_flat | D124: =Companions!D12 -> 20 | E124: =Companions!E12 -> 40000 | F124: =ROUND(D124/(E124/1000),2) -> 0.5 | G124: =IF(F124>=AVERAGE($F$114:$F$126)*1.2,"🟢 Bon deal",IF(F124<=AVERAGE($F$114:$F$126)*0.8,"🔴 Cher","🟡 Normal")) -> 🔴 Cher
A125: =Companions!A13 -> NEXUS - IA Rogue | B125: =Companions!B13 -> legendary | C125: =Companions!C13 -> cpc_flat | D125: =Companions!D13 -> 20 | E125: =Companions!E13 -> 100000 | F125: =ROUND(D125/(E125/1000),2) -> 0.2 | G125: =IF(F125>=AVERAGE($F$114:$F$126)*1.2,"🟢 Bon deal",IF(F125<=AVERAGE($F$114:$F$126)*0.8,"🔴 Cher","🟡 Normal")) -> 🔴 Cher
A126: =Companions!A14 -> Dragon Holographique | B126: =Companions!B14 -> legendary | C126: =Companions!C14 -> crit_chance | D126: =Companions!D14 -> 15 | E126: =Companions!E14 -> 150000 | F126: =ROUND(D126/(E126/1000),2) -> 0.1 | G126: =IF(F126>=AVERAGE($F$114:$F$126)*1.2,"🟢 Bon deal",IF(F126<=AVERAGE($F$114:$F$126)*0.8,"🔴 Cher","🟡 Normal")) -> 🔴 Cher
A129: 🎯 COMBAT SKILLS — EFFICACITÉ PAR SPEC
...
